{
  "version": 1,
  "records": [
    {
      "sourceBoardId": "227",
      "sourceBoardName": "immigration-monthly-statistics",
      "articleId": "604572",
      "articleTitle": "2026년 2월 출입국외국인정책 통계월보",
      "publishedAt": "2026.03.20",
      "attachmentId": "492254",
      "attachmentName": "1.2._외국인입국자(2월).xlsx",
      "attachmentUrl": "https://www.immigration.go.kr/bbs/immigration/227/492254/download.do",
      "localPath": "data/raw/2026/2026-02/1.2._외국인입국자(2월).xlsx",
      "downloadedAt": "2026-03-26T08:59:14.075Z",
      "status": "downloaded",
      "checksum": "7ef97d32085067a4f1ba8065567d2d86319bf6f1cd6136771f8bbff039928708"
    },
    {
      "sourceBoardId": "227",
      "sourceBoardName": "immigration-monthly-statistics",
      "articleId": "603637",
      "articleTitle": "2026년 1월 출입국외국인정책 통계월보",
      "publishedAt": "2026.02.20",
      "attachmentId": "492040",
      "attachmentName": "1.2._외국인입국자(1월).xlsx",
      "attachmentUrl": "https://www.immigration.go.kr/bbs/immigration/227/492040/download.do",
      "localPath": "data/raw/2026/2026-01/1.2._외국인입국자(1월).xlsx",
      "downloadedAt": "2026-03-26T08:59:14.208Z",
      "status": "downloaded",
      "checksum": "3c29bc4eeb46662ba3303da6b1a3fcd5e81e6b0807f479d20c0c4b07aa8a1d08"
    },
    {
      "sourceBoardId": "227",
      "sourceBoardName": "immigration-monthly-statistics",
      "articleId": "602699",
      "articleTitle": "2025년 12월 출입국외국인정책 통계월보",
      "publishedAt": "2026.01.21",
      "attachmentId": "489823",
      "attachmentName": "1.2._외국인입국자(12월).xlsx",
      "attachmentUrl": "https://www.immigration.go.kr/bbs/immigration/227/489823/download.do",
      "localPath": "data/raw/2025/2025-12/1.2._외국인입국자(12월).xlsx",
      "downloadedAt": "2026-03-26T08:59:14.322Z",
      "status": "downloaded",
      "checksum": "0685a6f9603a000558c2c8e3f3d34e01ff632558d37a9e62c41af9d3e7470fb0"
    },
    {
      "sourceBoardId": "227",
      "sourceBoardName": "immigration-monthly-statistics",
      "articleId": "601757",
      "articleTitle": "2025년 11월 출입국외국인정책 통계월보",
      "publishedAt": "2025.12.22",
      "attachmentId": "488675",
      "attachmentName": "1.2._외국인입국자(11월).xlsx",
      "attachmentUrl": "https://www.immigration.go.kr/bbs/immigration/227/488675/download.do",
      "localPath": "data/raw/2025/2025-11/1.2._외국인입국자(11월).xlsx",
      "downloadedAt": "2026-03-26T08:59:14.428Z",
      "status": "downloaded",
      "checksum": "0c498843dc2d096b27904810eb761d9d7267ec0aa35abcddf415281750488567"
    },
    {
      "sourceBoardId": "227",
      "sourceBoardName": "immigration-monthly-statistics",
      "articleId": "600754",
      "articleTitle": "2025년 10월 출입국외국인정책 통계월보",
      "publishedAt": "2025.11.20",
      "attachmentId": "487966",
      "attachmentName": "1.2._외국인입국자(10월).xlsx",
      "attachmentUrl": "https://www.immigration.go.kr/bbs/immigration/227/487966/download.do",
      "localPath": "data/raw/2025/2025-10/1.2._외국인입국자(10월).xlsx",
      "downloadedAt": "2026-03-26T08:59:14.551Z",
      "status": "downloaded",
      "checksum": "d8b0bdcd0e4283c2326cbf965bcdd026daa29b1a2ef49a065f5f32a09f7489c1"
    },
    {
      "sourceBoardId": "227",
      "sourceBoardName": "immigration-monthly-statistics",
      "articleId": "600056",
      "articleTitle": "2025년 9월 출입국외국인정책 통계월보",
      "publishedAt": "2025.10.31",
      "attachmentId": "486611",
      "attachmentName": "1.2._외국인입국자(9월).xlsx",
      "attachmentUrl": "https://www.immigration.go.kr/bbs/immigration/227/486611/download.do",
      "localPath": "data/raw/2025/2025-09/1.2._외국인입국자(9월).xlsx",
      "downloadedAt": "2026-03-26T08:59:14.667Z",
      "status": "downloaded",
      "checksum": "6fb6335475820485963b54ede8fa74471ab3046b99c7a73ddba909b6a9d1ac53"
    },
    {
      "sourceBoardId": "227",
      "sourceBoardName": "immigration-monthly-statistics",
      "articleId": "598954",
      "articleTitle": "2025년 8월 출입국외국인정책 통계월보",
      "publishedAt": "2025.09.19",
      "attachmentId": "485346",
      "attachmentName": "1.2._외국인입국자(8월).xlsx",
      "attachmentUrl": "https://www.immigration.go.kr/bbs/immigration/227/485346/download.do",
      "localPath": "data/raw/2025/2025-08/1.2._외국인입국자(8월).xlsx",
      "downloadedAt": "2026-03-26T08:59:14.758Z",
      "status": "downloaded",
      "checksum": "cc15d4a6caa051a92cbc589f7545e15db89d6070b0fee8d7780ddf5650b18a0b"
    },
    {
      "sourceBoardId": "227",
      "sourceBoardName": "immigration-monthly-statistics",
      "articleId": "598147",
      "articleTitle": "2025년 7월 출입국외국인정책 통계월보",
      "publishedAt": "2025.08.21",
      "attachmentId": "484423",
      "attachmentName": "1.2._외국인입국자(7월).xlsx",
      "attachmentUrl": "https://www.immigration.go.kr/bbs/immigration/227/484423/download.do",
      "localPath": "data/raw/2025/2025-07/1.2._외국인입국자(7월).xlsx",
      "downloadedAt": "2026-03-26T08:59:14.864Z",
      "status": "downloaded",
      "checksum": "47c08b878317ae1bb23c51e3180c807db1638511103a01d0f1566952232df0bd"
    },
    {
      "sourceBoardId": "227",
      "sourceBoardName": "immigration-monthly-statistics",
      "articleId": "597210",
      "articleTitle": "2025년 6월 출입국외국인정책 통계월보",
      "publishedAt": "2025.07.18",
      "attachmentId": "483372",
      "attachmentName": "1.2._외국인입국자(6월).xlsx",
      "attachmentUrl": "https://www.immigration.go.kr/bbs/immigration/227/483372/download.do",
      "localPath": "data/raw/2025/2025-06/1.2._외국인입국자(6월).xlsx",
      "downloadedAt": "2026-03-26T08:59:14.978Z",
      "status": "downloaded",
      "checksum": "d9c09aef8d573d5eb6f73e6e7179387389868e1407aa954ad6835c0714c94b85"
    },
    {
      "sourceBoardId": "227",
      "sourceBoardName": "immigration-monthly-statistics",
      "articleId": "596293",
      "articleTitle": "2025년 5월 출입국외국인정책 통계월보",
      "publishedAt": "2025.06.20",
      "attachmentId": "482305",
      "attachmentName": "1.2._외국인입국자(5월).xlsx",
      "attachmentUrl": "https://www.immigration.go.kr/bbs/immigration/227/482305/download.do",
      "localPath": "data/raw/2025/2025-05/1.2._외국인입국자(5월).xlsx",
      "downloadedAt": "2026-03-26T08:59:15.094Z",
      "status": "downloaded",
      "checksum": "f071e133df46d0b885218fb658305ef60426455e1a083818b308eb6e3e039664"
    },
    {
      "sourceBoardId": "227",
      "sourceBoardName": "immigration-monthly-statistics",
      "articleId": "595426",
      "articleTitle": "2025년 4월 출입국외국인정책 통계월보",
      "publishedAt": "2025.05.20",
      "attachmentId": "481364",
      "attachmentName": "1.2._외국인입국자(4월).xlsx",
      "attachmentUrl": "https://www.immigration.go.kr/bbs/immigration/227/481364/download.do",
      "localPath": "data/raw/2025/2025-04/1.2._외국인입국자(4월).xlsx",
      "downloadedAt": "2026-03-26T08:59:15.213Z",
      "status": "downloaded",
      "checksum": "4e7c507ea7ada3f2f91e311f11732aa5505671398feffc61b9a1ef98045484df"
    },
    {
      "sourceBoardId": "227",
      "sourceBoardName": "immigration-monthly-statistics",
      "articleId": "594384",
      "articleTitle": "2025년 3월 출입국외국인정책 통계월보",
      "publishedAt": "2025.04.18",
      "attachmentId": "480270",
      "attachmentName": "1.2._외국인입국자(3월).xlsx",
      "attachmentUrl": "https://www.immigration.go.kr/bbs/immigration/227/480270/download.do",
      "localPath": "data/raw/2025/2025-03/1.2._외국인입국자(3월).xlsx",
      "downloadedAt": "2026-03-26T08:59:15.325Z",
      "status": "downloaded",
      "checksum": "785b6e537845c08c3c2f641857c922c693e06fe58d2162d0ad93b4b24934bca5"
    },
    {
      "sourceBoardId": "227",
      "sourceBoardName": "immigration-monthly-statistics",
      "articleId": "593166",
      "articleTitle": "2025년 2월 출입국외국인정책 통계월보",
      "publishedAt": "2025.03.20",
      "attachmentId": "478991",
      "attachmentName": "1.2._외국인입국자(2월).xlsx",
      "attachmentUrl": "https://www.immigration.go.kr/bbs/immigration/227/478991/download.do",
      "localPath": "data/raw/2025/2025-02/1.2._외국인입국자(2월).xlsx",
      "downloadedAt": "2026-03-26T08:59:15.446Z",
      "status": "downloaded",
      "checksum": "c465e3ed8f8554aa6b1eff77380493f0e56d1961537d7e19c99f49fa084aea05"
    },
    {
      "sourceBoardId": "227",
      "sourceBoardName": "immigration-monthly-statistics",
      "articleId": "592109",
      "articleTitle": "2025년 1월 출입국외국인정책 통계월보",
      "publishedAt": "2025.02.19",
      "attachmentId": "477686",
      "attachmentName": "1.2._외국인입국자(1월).xlsx",
      "attachmentUrl": "https://www.immigration.go.kr/bbs/immigration/227/477686/download.do",
      "localPath": "data/raw/2025/2025-01/1.2._외국인입국자(1월).xlsx",
      "downloadedAt": "2026-03-26T08:59:15.551Z",
      "status": "downloaded",
      "checksum": "57af462c4faba455c1ad6e9e7ac7896eebb226557fedfe70879ebb91e0b33830"
    },
    {
      "sourceBoardId": "227",
      "sourceBoardName": "immigration-monthly-statistics",
      "articleId": "591331",
      "articleTitle": "2024년 12월 출입국외국인정책 통계월보",
      "publishedAt": "2025.01.20",
      "attachmentId": "476737",
      "attachmentName": "1.2_외국인 입국자 현황(12월).xlsx",
      "attachmentUrl": "https://www.immigration.go.kr/bbs/immigration/227/476737/download.do",
      "localPath": "data/raw/2024/2024-12/1.2_외국인 입국자 현황(12월).xlsx",
      "downloadedAt": "2026-03-26T08:59:15.653Z",
      "status": "downloaded",
      "checksum": "71494feacf92232f63b73b6aa0c47ed7c862f1604eb20fe19226e3a8d1de3318"
    },
    {
      "sourceBoardId": "227",
      "sourceBoardName": "immigration-monthly-statistics",
      "articleId": "590483",
      "articleTitle": "2024년 11월 출입국외국인정책 통계월보",
      "publishedAt": "2024.12.20",
      "attachmentId": "475739",
      "attachmentName": "1.2._외국인입국자(11월).xlsx",
      "attachmentUrl": "https://www.immigration.go.kr/bbs/immigration/227/475739/download.do",
      "localPath": "data/raw/2024/2024-11/1.2._외국인입국자(11월).xlsx",
      "downloadedAt": "2026-03-26T08:59:15.797Z",
      "status": "downloaded",
      "checksum": "0ad9ae9522c50022e0055f74a87acc4644a6ec4bcdf913c658ff6dfe8ac649ee"
    },
    {
      "sourceBoardId": "227",
      "sourceBoardName": "immigration-monthly-statistics",
      "articleId": "589585",
      "articleTitle": "2024년 10월 출입국외국인정책 통계월보",
      "publishedAt": "2024.11.20",
      "attachmentId": "474837",
      "attachmentName": "1.2._외국인입국자 현황(10월).xlsx",
      "attachmentUrl": "https://www.immigration.go.kr/bbs/immigration/227/474837/download.do",
      "localPath": "data/raw/2024/2024-10/1.2._외국인입국자 현황(10월).xlsx",
      "downloadedAt": "2026-03-26T08:59:15.887Z",
      "status": "downloaded",
      "checksum": "001919e4a9a6720de341d4cf2e1b42d11a0545b379591468b4bf85bb786eaace"
    },
    {
      "sourceBoardId": "227",
      "sourceBoardName": "immigration-monthly-statistics",
      "articleId": "588712",
      "articleTitle": "2024년 9월 출입국외국인정책 통계월보",
      "publishedAt": "2024.10.21",
      "attachmentId": "474827",
      "attachmentName": "1.2_외국인입국자 현황(9월).xlsx",
      "attachmentUrl": "https://www.immigration.go.kr/bbs/immigration/227/474827/download.do",
      "localPath": "data/raw/2024/2024-09/1.2_외국인입국자 현황(9월).xlsx",
      "downloadedAt": "2026-03-26T08:59:15.980Z",
      "status": "downloaded",
      "checksum": "66ba0b6fad1fc6fecca43d2d35b9fb1543e8432cef5d0d2fefc1d73918610369"
    },
    {
      "sourceBoardId": "227",
      "sourceBoardName": "immigration-monthly-statistics",
      "articleId": "587771",
      "articleTitle": "2024년 8월 출입국외국인정책 통계월보",
      "publishedAt": "2024.09.20",
      "attachmentId": "472813",
      "attachmentName": "2408_외국인입국자.xlsx",
      "attachmentUrl": "https://www.immigration.go.kr/bbs/immigration/227/472813/download.do",
      "localPath": "data/raw/2024/2024-08/2408_외국인입국자.xlsx",
      "downloadedAt": "2026-03-26T08:59:16.084Z",
      "status": "downloaded",
      "checksum": "88fb1643d57c6277fd0a840dd11809bf23e838f6c46e55f45e73c980a7dd141d"
    },
    {
      "sourceBoardId": "227",
      "sourceBoardName": "immigration-monthly-statistics",
      "articleId": "586477",
      "articleTitle": "2024년 7월 출입국외국인정책 통계월보",
      "publishedAt": "2024.08.20",
      "attachmentId": "471714",
      "attachmentName": "2407_외국인입국자.xlsx",
      "attachmentUrl": "https://www.immigration.go.kr/bbs/immigration/227/471714/download.do",
      "localPath": "data/raw/2024/2024-07/2407_외국인입국자.xlsx",
      "downloadedAt": "2026-03-26T08:59:16.182Z",
      "status": "downloaded",
      "checksum": "dfbc6c0edc3915d49a9aff42e962ec889f3c163bcdc232881676265c072306c0"
    },
    {
      "sourceBoardId": "227",
      "sourceBoardName": "immigration-monthly-statistics",
      "articleId": "585504",
      "articleTitle": "2024년 6월 출입국외국인정책 통계월보",
      "publishedAt": "2024.07.19",
      "attachmentId": "473837",
      "attachmentName": "1.2.외국인입국자.xlsx",
      "attachmentUrl": "https://www.immigration.go.kr/bbs/immigration/227/473837/download.do",
      "localPath": "data/raw/2024/2024-06/1.2.외국인입국자.xlsx",
      "downloadedAt": "2026-03-26T08:59:16.278Z",
      "status": "downloaded",
      "checksum": "77894d9e62e01943d79fe345674699f055506102dbe6ec6d25bea30a521e4bfb"
    },
    {
      "sourceBoardId": "227",
      "sourceBoardName": "immigration-monthly-statistics",
      "articleId": "584476",
      "articleTitle": "2024년 5월 출입국외국인정책 통계월보",
      "publishedAt": "2024.06.20",
      "attachmentId": "469370",
      "attachmentName": "2.xlsx",
      "attachmentUrl": "https://www.immigration.go.kr/bbs/immigration/227/469370/download.do",
      "localPath": "data/raw/2024/2024-05/2.xlsx",
      "downloadedAt": "2026-03-26T08:59:16.373Z",
      "status": "downloaded",
      "checksum": "0e364d774c6cf35634c13437f569c381d66180615eac771362af981bcd8572ec"
    },
    {
      "sourceBoardId": "227",
      "sourceBoardName": "immigration-monthly-statistics",
      "articleId": "582369",
      "articleTitle": "2024년 3월 출입국외국인정책 통계월보",
      "publishedAt": "2024.04.19",
      "attachmentId": "467024",
      "attachmentName": "2.xlsx",
      "attachmentUrl": "https://www.immigration.go.kr/bbs/immigration/227/467024/download.do",
      "localPath": "data/raw/2024/2024-03/2.xlsx",
      "downloadedAt": "2026-03-26T08:59:16.462Z",
      "status": "downloaded",
      "checksum": "44e69efcbbc86c45f90313b079449ff50df0e1b16bd4696402e34b82afed9027"
    },
    {
      "sourceBoardId": "227",
      "sourceBoardName": "immigration-monthly-statistics",
      "articleId": "580161",
      "articleTitle": "2024년 1월 출입국외국인정책 통계월보",
      "publishedAt": "2024.02.22",
      "attachmentId": "465409",
      "attachmentName": "2.xlsx",
      "attachmentUrl": "https://www.immigration.go.kr/bbs/immigration/227/465409/download.do",
      "localPath": "data/raw/2024/2024-01/2.xlsx",
      "downloadedAt": "2026-03-26T08:59:16.555Z",
      "status": "downloaded",
      "checksum": "5fc8aacb3a8ed148fdaa5cad6ab2105e47d316f65bf7f921f06031c9a1a95878"
    },
    {
      "sourceBoardId": "227",
      "sourceBoardName": "immigration-monthly-statistics",
      "articleId": "578968",
      "articleTitle": "2023년 12월 출입국외국인정책 통계월보",
      "publishedAt": "2024.01.11",
      "attachmentId": "463074",
      "attachmentName": "2.xlsx",
      "attachmentUrl": "https://www.immigration.go.kr/bbs/immigration/227/463074/download.do",
      "localPath": "data/raw/2023/2023-12/2.xlsx",
      "downloadedAt": "2026-03-26T08:59:16.652Z",
      "status": "downloaded",
      "checksum": "1f48d687e2f8d0149af05bd978e30d3f1a590f3ed000e1120463a1f2d0897187"
    },
    {
      "sourceBoardId": "227",
      "sourceBoardName": "immigration-monthly-statistics",
      "articleId": "578342",
      "articleTitle": "2023년 11월 출입국외국인정책 통계월보",
      "publishedAt": "2023.12.22",
      "attachmentId": "462829",
      "attachmentName": "2.xlsx",
      "attachmentUrl": "https://www.immigration.go.kr/bbs/immigration/227/462829/download.do",
      "localPath": "data/raw/2023/2023-11/2.xlsx",
      "downloadedAt": "2026-03-26T08:59:16.750Z",
      "status": "downloaded",
      "checksum": "43e79e7f8e7b3e9b5a9e2ca214150afdf8aba214fe31ef59d44cc6901cb68cd6"
    },
    {
      "sourceBoardId": "227",
      "sourceBoardName": "immigration-monthly-statistics",
      "articleId": "577439",
      "articleTitle": "2023년 10월 출입국외국인정책 통계월보",
      "publishedAt": "2023.11.23",
      "attachmentId": "461782",
      "attachmentName": "2.xlsx",
      "attachmentUrl": "https://www.immigration.go.kr/bbs/immigration/227/461782/download.do",
      "localPath": "data/raw/2023/2023-10/2.xlsx",
      "downloadedAt": "2026-03-26T08:59:16.845Z",
      "status": "downloaded",
      "checksum": "f4206002cb2ab2462a326385e42bb9b82bce92d0da84354c10eeba74dd351ddf"
    },
    {
      "sourceBoardId": "227",
      "sourceBoardName": "immigration-monthly-statistics",
      "articleId": "576318",
      "articleTitle": "2023년 9월 출입국외국인정책 통계월보",
      "publishedAt": "2023.10.20",
      "attachmentId": "461046",
      "attachmentName": "2.xlsx",
      "attachmentUrl": "https://www.immigration.go.kr/bbs/immigration/227/461046/download.do",
      "localPath": "data/raw/2023/2023-09/2.xlsx",
      "downloadedAt": "2026-03-26T08:59:16.934Z",
      "status": "downloaded",
      "checksum": "63cbf87459f6f773ad1678e4d1cefee67374230733972e4ca7dd33d3e71b3416"
    },
    {
      "sourceBoardId": "227",
      "sourceBoardName": "immigration-monthly-statistics",
      "articleId": "575396",
      "articleTitle": "2023년 8월 출입국외국인정책 통계월보",
      "publishedAt": "2023.09.21",
      "attachmentId": "461049",
      "attachmentName": "2.xlsx",
      "attachmentUrl": "https://www.immigration.go.kr/bbs/immigration/227/461049/download.do",
      "localPath": "data/raw/2023/2023-08/2.xlsx",
      "downloadedAt": "2026-03-26T08:59:17.020Z",
      "status": "downloaded",
      "checksum": "1d7bd280f4e3b326969b3f3580bd2c8c22407c0d2d1d3e42a318b2a642acc70e"
    },
    {
      "sourceBoardId": "227",
      "sourceBoardName": "immigration-monthly-statistics",
      "articleId": "574464",
      "articleTitle": "2023년 7월 출입국외국인정책 통계월보",
      "publishedAt": "2023.08.22",
      "attachmentId": "457687",
      "attachmentName": "2.xlsx",
      "attachmentUrl": "https://www.immigration.go.kr/bbs/immigration/227/457687/download.do",
      "localPath": "data/raw/2023/2023-07/2.xlsx",
      "downloadedAt": "2026-03-26T08:59:17.117Z",
      "status": "downloaded",
      "checksum": "f216e69a2d48b39b3fd58f28aed3e6d3422ffba8a633223619aded90ebdcd51f"
    },
    {
      "sourceBoardId": "227",
      "sourceBoardName": "immigration-monthly-statistics",
      "articleId": "573603",
      "articleTitle": "2023년 6월 출입국외국인정책 통계월보",
      "publishedAt": "2023.07.27",
      "attachmentId": "458113",
      "attachmentName": "2.xlsx",
      "attachmentUrl": "https://www.immigration.go.kr/bbs/immigration/227/458113/download.do",
      "localPath": "data/raw/2023/2023-06/2.xlsx",
      "downloadedAt": "2026-03-26T08:59:17.212Z",
      "status": "downloaded",
      "checksum": "c5ec7ddf43f84a3524a3b177a8e33de65a4d2dde9133d7fff5b7ae6e94e2b433"
    },
    {
      "sourceBoardId": "227",
      "sourceBoardName": "immigration-monthly-statistics",
      "articleId": "572189",
      "articleTitle": "2023년 5월 출입국외국인정책 통계월보",
      "publishedAt": "2023.06.19",
      "attachmentId": "455300",
      "attachmentName": "2.xlsx",
      "attachmentUrl": "https://www.immigration.go.kr/bbs/immigration/227/455300/download.do",
      "localPath": "data/raw/2023/2023-05/2.xlsx",
      "downloadedAt": "2026-03-26T08:59:17.337Z",
      "status": "downloaded",
      "checksum": "3b7b3686ac105a413e09a24606a29974f3d3f397dce7baadbb158e64642e4dc4"
    },
    {
      "sourceBoardId": "227",
      "sourceBoardName": "immigration-monthly-statistics",
      "articleId": "570996",
      "articleTitle": "2023년 4월 출입국외국인정책 통계월보",
      "publishedAt": "2023.05.17",
      "attachmentId": "454114",
      "attachmentName": "2.xlsx",
      "attachmentUrl": "https://www.immigration.go.kr/bbs/immigration/227/454114/download.do",
      "localPath": "data/raw/2023/2023-04/2.xlsx",
      "downloadedAt": "2026-03-26T08:59:17.452Z",
      "status": "downloaded",
      "checksum": "df7f4c5d56afeb9f4949c26ea720eb3be38aa0215075b96c044d6fdb32a266e7"
    },
    {
      "sourceBoardId": "227",
      "sourceBoardName": "immigration-monthly-statistics",
      "articleId": "569791",
      "articleTitle": "2023년 3월 출입국외국인정책 통계월보",
      "publishedAt": "2023.04.19",
      "attachmentId": "453607",
      "attachmentName": "2.xlsx",
      "attachmentUrl": "https://www.immigration.go.kr/bbs/immigration/227/453607/download.do",
      "localPath": "data/raw/2023/2023-03/2.xlsx",
      "downloadedAt": "2026-03-26T08:59:17.570Z",
      "status": "downloaded",
      "checksum": "90f70079343d9ffadba5a791e25ee3b2b25d5c5e48c754011887b149a8da6f6a"
    },
    {
      "sourceBoardId": "227",
      "sourceBoardName": "immigration-monthly-statistics",
      "articleId": "568801",
      "articleTitle": "2023년 2월 출입국외국인정책 통계월보",
      "publishedAt": "2023.03.20",
      "attachmentId": "452563",
      "attachmentName": "2.xlsx",
      "attachmentUrl": "https://www.immigration.go.kr/bbs/immigration/227/452563/download.do",
      "localPath": "data/raw/2023/2023-02/2.xlsx",
      "downloadedAt": "2026-03-26T08:59:17.699Z",
      "status": "downloaded",
      "checksum": "d0a834e1b9c65068d920f3e1e09187e381a6720c0d3b62110c1e01c1a68ad5b0"
    },
    {
      "sourceBoardId": "227",
      "sourceBoardName": "immigration-monthly-statistics",
      "articleId": "568051",
      "articleTitle": "2023년 1월 출입국외국인정책 통계월보",
      "publishedAt": "2023.02.24",
      "attachmentId": "450854",
      "attachmentName": "2.xlsx",
      "attachmentUrl": "https://www.immigration.go.kr/bbs/immigration/227/450854/download.do",
      "localPath": "data/raw/2023/2023-01/2.xlsx",
      "downloadedAt": "2026-03-26T08:59:17.793Z",
      "status": "downloaded",
      "checksum": "b288d40cc717dc47c35d4641bc553bf42efe2ea270020d451a84eff45dd55498"
    },
    {
      "sourceBoardId": "227",
      "sourceBoardName": "immigration-monthly-statistics",
      "articleId": "565985",
      "articleTitle": "2022년 11월 출입국외국인정책 통계월보",
      "publishedAt": "2022.12.23",
      "attachmentId": "448468",
      "attachmentName": "2.xlsx",
      "attachmentUrl": "https://www.immigration.go.kr/bbs/immigration/227/448468/download.do",
      "localPath": "data/raw/2022/2022-11/2.xlsx",
      "downloadedAt": "2026-03-26T08:59:17.894Z",
      "status": "downloaded",
      "checksum": "27d4eb2e54eb754147cb852905dad5ac4ab0d230aa2d49efa78aecd0a46ba340"
    },
    {
      "sourceBoardId": "227",
      "sourceBoardName": "immigration-monthly-statistics",
      "articleId": "564998",
      "articleTitle": "2022년 10월 출입국외국인정책 통계월보",
      "publishedAt": "2022.11.22",
      "attachmentId": "447290",
      "attachmentName": "2.xlsx",
      "attachmentUrl": "https://www.immigration.go.kr/bbs/immigration/227/447290/download.do",
      "localPath": "data/raw/2022/2022-10/2.xlsx",
      "downloadedAt": "2026-03-26T08:59:17.988Z",
      "status": "downloaded",
      "checksum": "4118fe68abce01984d996f71879ad64c2c7b60615b059aac96b6c60d7d6d0cf2"
    },
    {
      "sourceBoardId": "227",
      "sourceBoardName": "immigration-monthly-statistics",
      "articleId": "563200",
      "articleTitle": "2022년 8월 출입국외국인정책 통계월보",
      "publishedAt": "2022.09.23",
      "attachmentId": "445320",
      "attachmentName": "2.xlsx",
      "attachmentUrl": "https://www.immigration.go.kr/bbs/immigration/227/445320/download.do",
      "localPath": "data/raw/2022/2022-08/2.xlsx",
      "downloadedAt": "2026-03-26T08:59:18.091Z",
      "status": "downloaded",
      "checksum": "41695a0fe4544a0d73ecf4f942ffe06cdfe2264e67ef20906db7a0066dce0125"
    },
    {
      "sourceBoardId": "227",
      "sourceBoardName": "immigration-monthly-statistics",
      "articleId": "561361",
      "articleTitle": "2022년 6월 출입국외국인정책 통계월보",
      "publishedAt": "2022.07.20",
      "attachmentId": "443525",
      "attachmentName": "2.xlsx",
      "attachmentUrl": "https://www.immigration.go.kr/bbs/immigration/227/443525/download.do",
      "localPath": "data/raw/2022/2022-06/2.xlsx",
      "downloadedAt": "2026-03-26T08:59:18.191Z",
      "status": "downloaded",
      "checksum": "390f9ecde9b68129c9f0f9a017c008cb768c97fd5846973cc4dbc4c4ea831586"
    },
    {
      "sourceBoardId": "227",
      "sourceBoardName": "immigration-monthly-statistics",
      "articleId": "560452",
      "articleTitle": "2022년 5월 출입국외국인정책 통계월보",
      "publishedAt": "2022.06.22",
      "attachmentId": "442697",
      "attachmentName": "2.xlsx",
      "attachmentUrl": "https://www.immigration.go.kr/bbs/immigration/227/442697/download.do",
      "localPath": "data/raw/2022/2022-05/2.xlsx",
      "downloadedAt": "2026-03-26T08:59:18.286Z",
      "status": "downloaded",
      "checksum": "2e3a296024240bb910e4d359018965a6a6bf868f98999efa6764b50fc7d58ab5"
    },
    {
      "sourceBoardId": "227",
      "sourceBoardName": "immigration-monthly-statistics",
      "articleId": "559613",
      "articleTitle": "2022년 4월 출입국외국인정책 통계월보",
      "publishedAt": "2022.05.25",
      "attachmentId": "441735",
      "attachmentName": "2.xlsx",
      "attachmentUrl": "https://www.immigration.go.kr/bbs/immigration/227/441735/download.do",
      "localPath": "data/raw/2022/2022-04/2.xlsx",
      "downloadedAt": "2026-03-26T08:59:18.381Z",
      "status": "downloaded",
      "checksum": "1b94cc3000cfb1b6e6d56c6fa7b5d91266b3506e64585c0ed6920712a98f2fd6"
    },
    {
      "sourceBoardId": "227",
      "sourceBoardName": "immigration-monthly-statistics",
      "articleId": "557544",
      "articleTitle": "2022년 2월 출입국외국인정책 통계월보",
      "publishedAt": "2022.03.23",
      "attachmentId": "439556",
      "attachmentName": "2.xlsx",
      "attachmentUrl": "https://www.immigration.go.kr/bbs/immigration/227/439556/download.do",
      "localPath": "data/raw/2022/2022-02/2.xlsx",
      "downloadedAt": "2026-03-26T08:59:18.477Z",
      "status": "downloaded",
      "checksum": "4109acde91649c55cbe27953c5de55058ea9f2266158c1504ef056dafbc1b07e"
    },
    {
      "sourceBoardId": "227",
      "sourceBoardName": "immigration-monthly-statistics",
      "articleId": "556621",
      "articleTitle": "2022년 1월 출입국외국인정책 통계월보",
      "publishedAt": "2022.02.22",
      "attachmentId": "439562",
      "attachmentName": "2.xlsx",
      "attachmentUrl": "https://www.immigration.go.kr/bbs/immigration/227/439562/download.do",
      "localPath": "data/raw/2022/2022-01/2.xlsx",
      "downloadedAt": "2026-03-26T08:59:18.581Z",
      "status": "downloaded",
      "checksum": "42f9ffc3eaafd696a4b554d9be5d885a74781a5667af55e851e75e059336aacd"
    },
    {
      "sourceBoardId": "227",
      "sourceBoardName": "immigration-monthly-statistics",
      "articleId": "555809",
      "articleTitle": "2021년 12월 출입국외국인정책 통계월보",
      "publishedAt": "2022.01.25",
      "attachmentId": "437524",
      "attachmentName": "2.xlsx",
      "attachmentUrl": "https://www.immigration.go.kr/bbs/immigration/227/437524/download.do",
      "localPath": "data/raw/2021/2021-12/2.xlsx",
      "downloadedAt": "2026-03-26T08:59:18.675Z",
      "status": "downloaded",
      "checksum": "9c2a894342bcff4559ccb0170f9d3b9db93127cd05231f20e45216ef2dc8cf87"
    },
    {
      "sourceBoardId": "227",
      "sourceBoardName": "immigration-monthly-statistics",
      "articleId": "554760",
      "articleTitle": "2021년 11월 출입국외국인정책 통계월보",
      "publishedAt": "2021.12.21",
      "attachmentId": "436164",
      "attachmentName": "2.xlsx",
      "attachmentUrl": "https://www.immigration.go.kr/bbs/immigration/227/436164/download.do",
      "localPath": "data/raw/2021/2021-11/2.xlsx",
      "downloadedAt": "2026-03-26T08:59:18.761Z",
      "status": "downloaded",
      "checksum": "e0e3fb89698e1aeccdb3ff85e7de54a89e405e124716af817f957d6cbb155064"
    },
    {
      "sourceBoardId": "227",
      "sourceBoardName": "immigration-monthly-statistics",
      "articleId": "553900",
      "articleTitle": "2021년 10월 출입국외국인정책 통계월보",
      "publishedAt": "2021.11.23",
      "attachmentId": "435134",
      "attachmentName": "2.xlsx",
      "attachmentUrl": "https://www.immigration.go.kr/bbs/immigration/227/435134/download.do",
      "localPath": "data/raw/2021/2021-10/2.xlsx",
      "downloadedAt": "2026-03-26T08:59:18.873Z",
      "status": "downloaded",
      "checksum": "19004717e917284247d0e4ee8e6d6cbcb7b456b2861d65f9c7235f9e75c77670"
    },
    {
      "sourceBoardId": "227",
      "sourceBoardName": "immigration-monthly-statistics",
      "articleId": "552977",
      "articleTitle": "2021년 9월 출입국외국인정책 통계월보",
      "publishedAt": "2021.10.19",
      "attachmentId": "434007",
      "attachmentName": "2.xlsx",
      "attachmentUrl": "https://www.immigration.go.kr/bbs/immigration/227/434007/download.do",
      "localPath": "data/raw/2021/2021-09/2.xlsx",
      "downloadedAt": "2026-03-26T08:59:18.960Z",
      "status": "downloaded",
      "checksum": "996c5a7ad92fa1f7a9e45626a1a31621aa7e520d353dfa4eaf4fdb034f6d8457"
    },
    {
      "sourceBoardId": "227",
      "sourceBoardName": "immigration-monthly-statistics",
      "articleId": "552218",
      "articleTitle": "2021년 8월 출입국외국인정책 통계월보",
      "publishedAt": "2021.09.24",
      "attachmentId": "433109",
      "attachmentName": "2.xlsx",
      "attachmentUrl": "https://www.immigration.go.kr/bbs/immigration/227/433109/download.do",
      "localPath": "data/raw/2021/2021-08/2.xlsx",
      "downloadedAt": "2026-03-26T08:59:19.075Z",
      "status": "downloaded",
      "checksum": "1d0f23368afc151a113081f8fea255f4ce46838cce958a288efd292779741d13"
    },
    {
      "sourceBoardId": "227",
      "sourceBoardName": "immigration-monthly-statistics",
      "articleId": "551141",
      "articleTitle": "2021년 7월 출입국외국인정책 통계월보",
      "publishedAt": "2021.08.19",
      "attachmentId": "431902",
      "attachmentName": "2.xlsx",
      "attachmentUrl": "https://www.immigration.go.kr/bbs/immigration/227/431902/download.do",
      "localPath": "data/raw/2021/2021-07/2.xlsx",
      "downloadedAt": "2026-03-26T08:59:19.168Z",
      "status": "downloaded",
      "checksum": "60a676028d73b7c78c030d67ab6b417b8378311c530893e7df38100826aac136"
    },
    {
      "sourceBoardId": "227",
      "sourceBoardName": "immigration-monthly-statistics",
      "articleId": "550036",
      "articleTitle": "2021년 6월 출입국외국인정책 통계월보",
      "publishedAt": "2021.07.20",
      "attachmentId": "430802",
      "attachmentName": "2.xlsx",
      "attachmentUrl": "https://www.immigration.go.kr/bbs/immigration/227/430802/download.do",
      "localPath": "data/raw/2021/2021-06/2.xlsx",
      "downloadedAt": "2026-03-26T08:59:19.258Z",
      "status": "downloaded",
      "checksum": "50ad631b0e9fed5056ae655185af175dd8246de720efbb352b4c92085044419b"
    },
    {
      "sourceBoardId": "227",
      "sourceBoardName": "immigration-monthly-statistics",
      "articleId": "549156",
      "articleTitle": "2021년 5월 출입국외국인정책 통계월보",
      "publishedAt": "2021.06.23",
      "attachmentId": "429811",
      "attachmentName": "2.xlsx",
      "attachmentUrl": "https://www.immigration.go.kr/bbs/immigration/227/429811/download.do",
      "localPath": "data/raw/2021/2021-05/2.xlsx",
      "downloadedAt": "2026-03-26T08:59:19.353Z",
      "status": "downloaded",
      "checksum": "0a3d9b7aa09912f7c56cee77a3b59e95e42d55cebef6cbefdb1e77f027f717c4"
    },
    {
      "sourceBoardId": "227",
      "sourceBoardName": "immigration-monthly-statistics",
      "articleId": "547928",
      "articleTitle": "2021년 4월 출입국외국인정책 통계월보",
      "publishedAt": "2021.05.18",
      "attachmentId": "428413",
      "attachmentName": "2.xlsx",
      "attachmentUrl": "https://www.immigration.go.kr/bbs/immigration/227/428413/download.do",
      "localPath": "data/raw/2021/2021-04/2.xlsx",
      "downloadedAt": "2026-03-26T08:59:19.442Z",
      "status": "downloaded",
      "checksum": "7af22b02ae4858610df654b210f81aa3f4f4c0d940d933bfaef7b36b9c851088"
    },
    {
      "sourceBoardId": "227",
      "sourceBoardName": "immigration-monthly-statistics",
      "articleId": "546763",
      "articleTitle": "2021년 3월 출입국외국인정책 통계월보",
      "publishedAt": "2021.04.20",
      "attachmentId": "427237",
      "attachmentName": "2.xlsx",
      "attachmentUrl": "https://www.immigration.go.kr/bbs/immigration/227/427237/download.do",
      "localPath": "data/raw/2021/2021-03/2.xlsx",
      "downloadedAt": "2026-03-26T08:59:19.532Z",
      "status": "downloaded",
      "checksum": "4f3c6254d3dea609ac8510b7c967cbb64463b410ae919ebc5edcabaac5a37bf5"
    },
    {
      "sourceBoardId": "227",
      "sourceBoardName": "immigration-monthly-statistics",
      "articleId": "545267",
      "articleTitle": "2021년 2월 출입국외국인정책 통계월보",
      "publishedAt": "2021.03.23",
      "attachmentId": "425607",
      "attachmentName": "2.xlsx",
      "attachmentUrl": "https://www.immigration.go.kr/bbs/immigration/227/425607/download.do",
      "localPath": "data/raw/2021/2021-02/2.xlsx",
      "downloadedAt": "2026-03-26T08:59:19.626Z",
      "status": "downloaded",
      "checksum": "0ecfa78ecc74e2666c1c59cf71d7ecad23855914355c0b667a4deb42b9937b22"
    },
    {
      "sourceBoardId": "227",
      "sourceBoardName": "immigration-monthly-statistics",
      "articleId": "544243",
      "articleTitle": "2021년 1월 출입국외국인정책 통계월보",
      "publishedAt": "2021.03.04",
      "attachmentId": "424792",
      "attachmentName": "2.xlsx",
      "attachmentUrl": "https://www.immigration.go.kr/bbs/immigration/227/424792/download.do",
      "localPath": "data/raw/2021/2021-01/2.xlsx",
      "downloadedAt": "2026-03-26T08:59:19.710Z",
      "status": "downloaded",
      "checksum": "d95c4af9d22177d07c45edf41294682107a5259dc6e35f3ca89b2640eceb2150"
    },
    {
      "sourceBoardId": "227",
      "sourceBoardName": "immigration-monthly-statistics",
      "articleId": "543039",
      "articleTitle": "2020년 12월 출입국외국인정책 통계월보",
      "publishedAt": "2021.02.08",
      "attachmentId": "423478",
      "attachmentName": "2.xlsx",
      "attachmentUrl": "https://www.immigration.go.kr/bbs/immigration/227/423478/download.do",
      "localPath": "data/raw/2020/2020-12/2.xlsx",
      "downloadedAt": "2026-03-26T08:59:19.808Z",
      "status": "downloaded",
      "checksum": "536f51dc362642ddb4794a2e48cd78f277908edfdd3d2bffa2c60b5640ea6dbe"
    },
    {
      "sourceBoardId": "227",
      "sourceBoardName": "immigration-monthly-statistics",
      "articleId": "542453",
      "articleTitle": "2020년 11월 출입국외국인정책 통계월보",
      "publishedAt": "2021.01.29",
      "attachmentId": "422906",
      "attachmentName": "2.xlsx",
      "attachmentUrl": "https://www.immigration.go.kr/bbs/immigration/227/422906/download.do",
      "localPath": "data/raw/2020/2020-11/2.xlsx",
      "downloadedAt": "2026-03-26T08:59:19.917Z",
      "status": "downloaded",
      "checksum": "64cfb2fbc336606ba4140cb8482d3bca5abb2d854e8378b96029ec1120c4b9fd"
    },
    {
      "sourceBoardId": "227",
      "sourceBoardName": "immigration-monthly-statistics",
      "articleId": "541300",
      "articleTitle": "2020년 10월 출입국외국인정책 통계월보",
      "publishedAt": "2021.01.08",
      "attachmentId": "421774",
      "attachmentName": "2.xlsx",
      "attachmentUrl": "https://www.immigration.go.kr/bbs/immigration/227/421774/download.do",
      "localPath": "data/raw/2020/2020-10/2.xlsx",
      "downloadedAt": "2026-03-26T08:59:20.017Z",
      "status": "downloaded",
      "checksum": "e5b0a77a2d972a66857991244cb66471646784841649a2ed2de4ecb6545edf40"
    },
    {
      "sourceBoardId": "227",
      "sourceBoardName": "immigration-monthly-statistics",
      "articleId": "534005",
      "articleTitle": "2020년 9월 출입국외국인정책 통계월보",
      "publishedAt": "2020.11.18",
      "attachmentId": "419803",
      "attachmentName": "2.xlsx",
      "attachmentUrl": "https://www.immigration.go.kr/bbs/immigration/227/419803/download.do",
      "localPath": "data/raw/2020/2020-09/2.xlsx",
      "downloadedAt": "2026-03-26T08:59:20.116Z",
      "status": "downloaded",
      "checksum": "4436aa1fbeb2105aa705f6e4958aa7e96fef7465b32b4dd0ddf4d632eb4eb596"
    },
    {
      "sourceBoardId": "227",
      "sourceBoardName": "immigration-monthly-statistics",
      "articleId": "532900",
      "articleTitle": "2020년 8월 출입국외국인정책 통계월보",
      "publishedAt": "2020.10.28",
      "attachmentId": "419804",
      "attachmentName": "2.xlsx",
      "attachmentUrl": "https://www.immigration.go.kr/bbs/immigration/227/419804/download.do",
      "localPath": "data/raw/2020/2020-08/2.xlsx",
      "downloadedAt": "2026-03-26T08:59:20.202Z",
      "status": "downloaded",
      "checksum": "29688dfdc7c778977290807d891da89f1ec54cb135e12e3cdc68b758dab77e5d"
    },
    {
      "sourceBoardId": "227",
      "sourceBoardName": "immigration-monthly-statistics",
      "articleId": "532899",
      "articleTitle": "2020년 7월 출입국외국인정책 통계월보",
      "publishedAt": "2020.10.28",
      "attachmentId": "418116",
      "attachmentName": "2.xlsx",
      "attachmentUrl": "https://www.immigration.go.kr/bbs/immigration/227/418116/download.do",
      "localPath": "data/raw/2020/2020-07/2.xlsx",
      "downloadedAt": "2026-03-26T08:59:20.292Z",
      "status": "downloaded",
      "checksum": "fa48095fa24f954263df0bc82578657a1967422e1432233e24ba0d14310ad31c"
    },
    {
      "sourceBoardId": "227",
      "sourceBoardName": "immigration-monthly-statistics",
      "articleId": "530373",
      "articleTitle": "2020년 6월 출입국외국인정책 통계월보",
      "publishedAt": "2020.09.03",
      "attachmentId": "415559",
      "attachmentName": "2.xlsx",
      "attachmentUrl": "https://www.immigration.go.kr/bbs/immigration/227/415559/download.do",
      "localPath": "data/raw/2020/2020-06/2.xlsx",
      "downloadedAt": "2026-03-26T08:59:20.384Z",
      "status": "downloaded",
      "checksum": "a4521af166b87498db7ccd01d9c858984c1be6bddaa5b97e670e8a9599e39cd2"
    },
    {
      "sourceBoardId": "227",
      "sourceBoardName": "immigration-monthly-statistics",
      "articleId": "529717",
      "articleTitle": "2020년 5월 출입국외국인정책 통계월보",
      "publishedAt": "2020.08.21",
      "attachmentId": "414880",
      "attachmentName": "2.xlsx",
      "attachmentUrl": "https://www.immigration.go.kr/bbs/immigration/227/414880/download.do",
      "localPath": "data/raw/2020/2020-05/2.xlsx",
      "downloadedAt": "2026-03-26T08:59:20.473Z",
      "status": "downloaded",
      "checksum": "9d87f8879dd15da29de3f4bc5a239cb07ce7cc89d05ab38804ccd1e41be319df"
    },
    {
      "sourceBoardId": "227",
      "sourceBoardName": "immigration-monthly-statistics",
      "articleId": "524955",
      "articleTitle": "2020년 4월 출입국외국인정책통계월보",
      "publishedAt": "2020.05.22",
      "attachmentId": "410258",
      "attachmentName": "2.xlsx",
      "attachmentUrl": "https://www.immigration.go.kr/bbs/immigration/227/410258/download.do",
      "localPath": "data/raw/2020/2020-04/2.xlsx",
      "downloadedAt": "2026-03-26T08:59:20.554Z",
      "status": "downloaded",
      "checksum": "2e27911cbd775a06821794e7b0e1bf065f97b79b36ee4b3e144376d0d1c79156"
    },
    {
      "sourceBoardId": "227",
      "sourceBoardName": "immigration-monthly-statistics",
      "articleId": "523154",
      "articleTitle": "2020년 3월 출입국외국인정책 통계월보",
      "publishedAt": "2020.04.23",
      "attachmentId": "408851",
      "attachmentName": "2.xlsx",
      "attachmentUrl": "https://www.immigration.go.kr/bbs/immigration/227/408851/download.do",
      "localPath": "data/raw/2020/2020-03/2.xlsx",
      "downloadedAt": "2026-03-26T08:59:20.641Z",
      "status": "downloaded",
      "checksum": "d41ed8e42c1d870f312b3ae686ee07c4c4c1bed89850f6c6e0e43530c5aa490d"
    },
    {
      "sourceBoardId": "227",
      "sourceBoardName": "immigration-monthly-statistics",
      "articleId": "521714",
      "articleTitle": "2020년 2월 출입국외국인정책 통계월보",
      "publishedAt": "2020.03.26",
      "attachmentId": "407358",
      "attachmentName": "2.xlsx",
      "attachmentUrl": "https://www.immigration.go.kr/bbs/immigration/227/407358/download.do",
      "localPath": "data/raw/2020/2020-02/2.xlsx",
      "downloadedAt": "2026-03-26T08:59:20.753Z",
      "status": "downloaded",
      "checksum": "52915deaf8350be5c05402dc27fc0a007ed4a49434982218d7e4cb83aced6f81"
    },
    {
      "sourceBoardId": "227",
      "sourceBoardName": "immigration-monthly-statistics",
      "articleId": "521135",
      "articleTitle": "2020년 1월 출입국외국인정책 통계월보",
      "publishedAt": "2020.03.11",
      "attachmentId": "406839",
      "attachmentName": "2.xlsx",
      "attachmentUrl": "https://www.immigration.go.kr/bbs/immigration/227/406839/download.do",
      "localPath": "data/raw/2020/2020-01/2.xlsx",
      "downloadedAt": "2026-03-26T08:59:20.842Z",
      "status": "downloaded",
      "checksum": "5770cc9b9e3beedbe1eb27b1b4c3ea2bc737703124c969fefb6d4b84f466586d"
    },
    {
      "sourceBoardId": "227",
      "sourceBoardName": "immigration-monthly-statistics",
      "articleId": "519935",
      "articleTitle": "2019년 12월호 출입국외국인정책 통계월보",
      "publishedAt": "2020.02.14",
      "attachmentId": "405454",
      "attachmentName": "2.xlsx",
      "attachmentUrl": "https://www.immigration.go.kr/bbs/immigration/227/405454/download.do",
      "localPath": "data/raw/2019/2019-12/2.xlsx",
      "downloadedAt": "2026-03-26T08:59:20.932Z",
      "status": "downloaded",
      "checksum": "8d2c713781a3b1bde5077f9ff4cd7b6a662a1783f48ec6933f7cea134ac907c6"
    },
    {
      "sourceBoardId": "227",
      "sourceBoardName": "immigration-monthly-statistics",
      "articleId": "517128",
      "articleTitle": "2019년 11월호 출입국외국인정책 통계월보",
      "publishedAt": "2019.12.20",
      "attachmentId": "402627",
      "attachmentName": "2.xlsx",
      "attachmentUrl": "https://www.immigration.go.kr/bbs/immigration/227/402627/download.do",
      "localPath": "data/raw/2019/2019-11/2.xlsx",
      "downloadedAt": "2026-03-26T08:59:21.032Z",
      "status": "downloaded",
      "checksum": "b26d74a06151472bfa811ce449211f81c08f9098a215783bd179d3c37fd2407c"
    },
    {
      "sourceBoardId": "227",
      "sourceBoardName": "immigration-monthly-statistics",
      "articleId": "515726",
      "articleTitle": "2019년 10월호 출입국외국인정책 통계월보",
      "publishedAt": "2019.11.22",
      "attachmentId": "401302",
      "attachmentName": "2.xlsx",
      "attachmentUrl": "https://www.immigration.go.kr/bbs/immigration/227/401302/download.do",
      "localPath": "data/raw/2019/2019-10/2.xlsx",
      "downloadedAt": "2026-03-26T08:59:21.129Z",
      "status": "downloaded",
      "checksum": "3e992941016a01940a6415dc3ab83aec457c4dfe24f9e9a118f5c7d907bc0bb1"
    },
    {
      "sourceBoardId": "227",
      "sourceBoardName": "immigration-monthly-statistics",
      "articleId": "514076",
      "articleTitle": "2019년 9월호 출입국외국인정책 통계월보",
      "publishedAt": "2019.10.17",
      "attachmentId": "399814",
      "attachmentName": "2.xlsx",
      "attachmentUrl": "https://www.immigration.go.kr/bbs/immigration/227/399814/download.do",
      "localPath": "data/raw/2019/2019-09/2.xlsx",
      "downloadedAt": "2026-03-26T08:59:21.241Z",
      "status": "downloaded",
      "checksum": "33b3b311481b9ea09f1548db1664eecc2b4d34d5fe8ba281d99d805880a9196d"
    },
    {
      "sourceBoardId": "227",
      "sourceBoardName": "immigration-monthly-statistics",
      "articleId": "510883",
      "articleTitle": "2019년 8월호 출입국외국인정책 통계월보",
      "publishedAt": "2019.09.20",
      "attachmentId": "398655",
      "attachmentName": "2.xlsx",
      "attachmentUrl": "https://www.immigration.go.kr/bbs/immigration/227/398655/download.do",
      "localPath": "data/raw/2019/2019-08/2.xlsx",
      "downloadedAt": "2026-03-26T08:59:21.353Z",
      "status": "downloaded",
      "checksum": "771bdb93721d25221d8ed2ad1732eac8a7e10dcd7fe1f094308cee56ac296261"
    },
    {
      "sourceBoardId": "227",
      "sourceBoardName": "immigration-monthly-statistics",
      "articleId": "505066",
      "articleTitle": "2019년 7월호 출입국외국인정책 통계월보",
      "publishedAt": "2019.08.20",
      "attachmentId": "397423",
      "attachmentName": "2.xlsx",
      "attachmentUrl": "https://www.immigration.go.kr/bbs/immigration/227/397423/download.do",
      "localPath": "data/raw/2019/2019-07/2.xlsx",
      "downloadedAt": "2026-03-26T08:59:21.444Z",
      "status": "downloaded",
      "checksum": "5a58500884191bdf15a2c90e40cb7caee6f56a5bf5fedff3d3c1939746711032"
    },
    {
      "sourceBoardId": "227",
      "sourceBoardName": "immigration-monthly-statistics",
      "articleId": "503720",
      "articleTitle": "2019년 6월호 출입국외국인정책 통계월보",
      "publishedAt": "2019.07.18",
      "attachmentId": "395742",
      "attachmentName": "2.xlsx",
      "attachmentUrl": "https://www.immigration.go.kr/bbs/immigration/227/395742/download.do",
      "localPath": "data/raw/2019/2019-06/2.xlsx",
      "downloadedAt": "2026-03-26T08:59:21.533Z",
      "status": "downloaded",
      "checksum": "a4e824aefb8e174c7ea8f11e220dc2501e7d0b332b306e0e5be8dab3a8fe5dd4"
    },
    {
      "sourceBoardId": "227",
      "sourceBoardName": "immigration-monthly-statistics",
      "articleId": "502500",
      "articleTitle": "2019년 5월호 출입국외국인정책 통계월보",
      "publishedAt": "2019.06.20",
      "attachmentId": "394476",
      "attachmentName": "2.xlsx",
      "attachmentUrl": "https://www.immigration.go.kr/bbs/immigration/227/394476/download.do",
      "localPath": "data/raw/2019/2019-05/2.xlsx",
      "downloadedAt": "2026-03-26T08:59:21.633Z",
      "status": "downloaded",
      "checksum": "e660ba47613036b4c82a45f522b19abb45c9046f452b965da955fa9c7cfe6cc8"
    },
    {
      "sourceBoardId": "227",
      "sourceBoardName": "immigration-monthly-statistics",
      "articleId": "501245",
      "articleTitle": "2019년 4월호 출입국외국인정책 통계월보",
      "publishedAt": "2019.05.24",
      "attachmentId": "393290",
      "attachmentName": "2.xlsx",
      "attachmentUrl": "https://www.immigration.go.kr/bbs/immigration/227/393290/download.do",
      "localPath": "data/raw/2019/2019-04/2.xlsx",
      "downloadedAt": "2026-03-26T08:59:21.730Z",
      "status": "downloaded",
      "checksum": "4b6d8f3cb3a0e00d2f870d23bf69ca768059ad3703b26fb4259ab5525824c78e"
    },
    {
      "sourceBoardId": "227",
      "sourceBoardName": "immigration-monthly-statistics",
      "articleId": "490892",
      "articleTitle": "2019년 3월호 출입국외국인정책 통계월보",
      "publishedAt": "2019.04.19",
      "attachmentId": "393007",
      "attachmentName": "2.xlsx",
      "attachmentUrl": "https://www.immigration.go.kr/bbs/immigration/227/393007/download.do",
      "localPath": "data/raw/2019/2019-03/2.xlsx",
      "downloadedAt": "2026-03-26T08:59:21.817Z",
      "status": "downloaded",
      "checksum": "d9eca6b44fee47799af582d34a589a500de58e46170dffae14667231cfb1aa46"
    },
    {
      "sourceBoardId": "227",
      "sourceBoardName": "immigration-monthly-statistics",
      "articleId": "489549",
      "articleTitle": "2019년 2월호 출입국외국인정책 통계월보",
      "publishedAt": "2019.03.19",
      "attachmentId": "393009",
      "attachmentName": "2.xlsx",
      "attachmentUrl": "https://www.immigration.go.kr/bbs/immigration/227/393009/download.do",
      "localPath": "data/raw/2019/2019-02/2.xlsx",
      "downloadedAt": "2026-03-26T08:59:21.930Z",
      "status": "downloaded",
      "checksum": "1c48eede3ac7ab6a46933bdfd2c80cd1281e4bade2a930f81e1e2bcd7930c417"
    },
    {
      "sourceBoardId": "227",
      "sourceBoardName": "immigration-monthly-statistics",
      "articleId": "488581",
      "articleTitle": "2019년 1월호 출입국외국인정책 통계월보",
      "publishedAt": "2019.02.22",
      "attachmentId": "396445",
      "attachmentName": "2.xlsx",
      "attachmentUrl": "https://www.immigration.go.kr/bbs/immigration/227/396445/download.do",
      "localPath": "data/raw/2019/2019-01/2.xlsx",
      "downloadedAt": "2026-03-26T08:59:22.028Z",
      "status": "downloaded",
      "checksum": "798fd985ae12e01c35926d3b8e9ae51ee893b9d299d6240207cc273291ed0cf4"
    },
    {
      "sourceBoardId": "227",
      "sourceBoardName": "immigration-monthly-statistics",
      "articleId": "487406",
      "articleTitle": "2018년 12월호 출입국외국인정책 통계월보",
      "publishedAt": "2019.01.21",
      "attachmentId": "387925",
      "attachmentName": "2.xlsx",
      "attachmentUrl": "https://www.immigration.go.kr/bbs/immigration/227/387925/download.do",
      "localPath": "data/raw/2018/2018-12/2.xlsx",
      "downloadedAt": "2026-03-26T08:59:22.134Z",
      "status": "downloaded",
      "checksum": "81a8abf46fe64a38d271746a8823b0fb76b4a02227f0f606de925160b9184295"
    },
    {
      "sourceBoardId": "227",
      "sourceBoardName": "immigration-monthly-statistics",
      "articleId": "440603",
      "articleTitle": "2018년 11월호 출입국외국인정책 통계월보",
      "publishedAt": "2018.12.19",
      "attachmentId": "337021",
      "attachmentName": "2.xlsx",
      "attachmentUrl": "https://www.immigration.go.kr/bbs/immigration/227/337021/download.do",
      "localPath": "data/raw/2018/2018-11/2.xlsx",
      "downloadedAt": "2026-03-26T08:59:22.251Z",
      "status": "downloaded",
      "checksum": "3de1ed43859c68785e25d18825d919d5fe91e7c38bc364f01afe183e9449ea70"
    },
    {
      "sourceBoardId": "227",
      "sourceBoardName": "immigration-monthly-statistics",
      "articleId": "440602",
      "articleTitle": "2018년 10월호 출입국외국인정책 통계월보",
      "publishedAt": "2018.11.20",
      "attachmentId": "337017",
      "attachmentName": "2.xlsx",
      "attachmentUrl": "https://www.immigration.go.kr/bbs/immigration/227/337017/download.do",
      "localPath": "data/raw/2018/2018-10/2.xlsx",
      "downloadedAt": "2026-03-26T08:59:22.350Z",
      "status": "downloaded",
      "checksum": "febdca66096694d52f4c2cb5ad441402d3cab52e8ec9289226ff056029c23efb"
    },
    {
      "sourceBoardId": "227",
      "sourceBoardName": "immigration-monthly-statistics",
      "articleId": "440598",
      "articleTitle": "2018년 9월호 출입국외국인정책 통계월보",
      "publishedAt": "2018.10.19",
      "attachmentId": "337008",
      "attachmentName": "2.xlsx",
      "attachmentUrl": "https://www.immigration.go.kr/bbs/immigration/227/337008/download.do",
      "localPath": "data/raw/2018/2018-09/2.xlsx",
      "downloadedAt": "2026-03-26T08:59:22.445Z",
      "status": "downloaded",
      "checksum": "338d659826f32af52c06551de8a33ea1dbd09512b3775d0564a710a9c4dbdadb"
    },
    {
      "sourceBoardId": "227",
      "sourceBoardName": "immigration-monthly-statistics",
      "articleId": "440597",
      "articleTitle": "2018년 8월호 출입국외국인정책 통계월보",
      "publishedAt": "2018.09.19",
      "attachmentId": "337005",
      "attachmentName": "2.xlsx",
      "attachmentUrl": "https://www.immigration.go.kr/bbs/immigration/227/337005/download.do",
      "localPath": "data/raw/2018/2018-08/2.xlsx",
      "downloadedAt": "2026-03-26T08:59:22.537Z",
      "status": "downloaded",
      "checksum": "416381eda914509e5070d1c4c86f4e3009eaa9047ff7b54616fc125b56d826f1"
    },
    {
      "sourceBoardId": "227",
      "sourceBoardName": "immigration-monthly-statistics",
      "articleId": "440596",
      "articleTitle": "2018년 7월호 출입국외국인정책 통계월보",
      "publishedAt": "2018.08.23",
      "attachmentId": "337002",
      "attachmentName": "2.xls",
      "attachmentUrl": "https://www.immigration.go.kr/bbs/immigration/227/337002/download.do",
      "localPath": "data/raw/2018/2018-07/2.xls",
      "downloadedAt": "2026-03-26T08:59:22.642Z",
      "status": "downloaded",
      "checksum": "e583abd272f4082964a226bd89cc143fe09513578b6b74123ef4dece84eeeb77"
    },
    {
      "sourceBoardId": "227",
      "sourceBoardName": "immigration-monthly-statistics",
      "articleId": "440592",
      "articleTitle": "2018년 6월호 출입국외국인정책 통계월보",
      "publishedAt": "2018.07.17",
      "attachmentId": "336990",
      "attachmentName": "2.xls",
      "attachmentUrl": "https://www.immigration.go.kr/bbs/immigration/227/336990/download.do",
      "localPath": "data/raw/2018/2018-06/2.xls",
      "downloadedAt": "2026-03-26T08:59:22.750Z",
      "status": "downloaded",
      "checksum": "25541a6a081432fbd9b959d4d5ecdcee33c1f5625576aa0c929f95261a2b54a9"
    },
    {
      "sourceBoardId": "227",
      "sourceBoardName": "immigration-monthly-statistics",
      "articleId": "440591",
      "articleTitle": "2018년 5월호 출입국외국인정책 통계월보",
      "publishedAt": "2018.06.19",
      "attachmentId": "336987",
      "attachmentName": "2.xls",
      "attachmentUrl": "https://www.immigration.go.kr/bbs/immigration/227/336987/download.do",
      "localPath": "data/raw/2018/2018-05/2.xls",
      "downloadedAt": "2026-03-26T08:59:22.846Z",
      "status": "downloaded",
      "checksum": "e27b8cba62f3268edba375d5181fdbb52688ac9478a6abe7dac4c8bb2ed591b6"
    },
    {
      "sourceBoardId": "227",
      "sourceBoardName": "immigration-monthly-statistics",
      "articleId": "440590",
      "articleTitle": "2018년 4월호 출입국외국인정책 통계월보",
      "publishedAt": "2018.05.16",
      "attachmentId": "336983",
      "attachmentName": "2.xls",
      "attachmentUrl": "https://www.immigration.go.kr/bbs/immigration/227/336983/download.do",
      "localPath": "data/raw/2018/2018-04/2.xls",
      "downloadedAt": "2026-03-26T08:59:22.926Z",
      "status": "downloaded",
      "checksum": "f434def5e91cb821afda819926e77e8d38f28b2f3a9c7f062a2155fef8672800"
    },
    {
      "sourceBoardId": "227",
      "sourceBoardName": "immigration-monthly-statistics",
      "articleId": "440585",
      "articleTitle": "2018년 3월호 출입국외국인정책 통계월보",
      "publishedAt": "2018.04.17",
      "attachmentId": "336972",
      "attachmentName": "2.xls",
      "attachmentUrl": "https://www.immigration.go.kr/bbs/immigration/227/336972/download.do",
      "localPath": "data/raw/2018/2018-03/2.xls",
      "downloadedAt": "2026-03-26T08:59:23.013Z",
      "status": "downloaded",
      "checksum": "701e4669b3578eedf192c55e822c560820c476aa47df01b3bcd240050394fcdf"
    },
    {
      "sourceBoardId": "227",
      "sourceBoardName": "immigration-monthly-statistics",
      "articleId": "440584",
      "articleTitle": "2018년 2월호 출입국외국인정책 통계월보",
      "publishedAt": "2018.03.19",
      "attachmentId": "336969",
      "attachmentName": "2.xls",
      "attachmentUrl": "https://www.immigration.go.kr/bbs/immigration/227/336969/download.do",
      "localPath": "data/raw/2018/2018-02/2.xls",
      "downloadedAt": "2026-03-26T08:59:23.115Z",
      "status": "downloaded",
      "checksum": "89cfee815f54bee8c56f67b6a50bcbdff72863d4547b49af49b4ca13419508ac"
    },
    {
      "sourceBoardId": "227",
      "sourceBoardName": "immigration-monthly-statistics",
      "articleId": "440583",
      "articleTitle": "2018년 1월호 출입국외국인정책 통계월보",
      "publishedAt": "2018.02.23",
      "attachmentId": "336965",
      "attachmentName": "2.xls",
      "attachmentUrl": "https://www.immigration.go.kr/bbs/immigration/227/336965/download.do",
      "localPath": "data/raw/2018/2018-01/2.xls",
      "downloadedAt": "2026-03-26T08:59:23.214Z",
      "status": "downloaded",
      "checksum": "a577d7549158a550f7b6a82286f524c08a483f23deef8d0711c6ff087ab3e072"
    },
    {
      "sourceBoardId": "227",
      "sourceBoardName": "immigration-monthly-statistics",
      "articleId": "440579",
      "articleTitle": "2017년 12월호 출입국외국인정책 통계월보",
      "publishedAt": "2018.01.25",
      "attachmentId": "336955",
      "attachmentName": "2.xls",
      "attachmentUrl": "https://www.immigration.go.kr/bbs/immigration/227/336955/download.do",
      "localPath": "data/raw/2017/2017-12/2.xls",
      "downloadedAt": "2026-03-26T08:59:23.305Z",
      "status": "downloaded",
      "checksum": "5e0f0489fa6a0d646721ca633a02766eecd5492a4544334fb9386f76ca892af7"
    },
    {
      "sourceBoardId": "227",
      "sourceBoardName": "immigration-monthly-statistics",
      "articleId": "327506",
      "articleTitle": "2017년 11월호 출입국외국인정책 통계월보",
      "publishedAt": "2017.12.19",
      "attachmentId": "277140",
      "attachmentName": "2.xls",
      "attachmentUrl": "https://www.immigration.go.kr/bbs/immigration/227/277140/download.do",
      "localPath": "data/raw/2017/2017-11/2.xls",
      "downloadedAt": "2026-03-26T08:59:23.398Z",
      "status": "downloaded",
      "checksum": "f39d3193a7c6cab4c94583761e5862437d7b28a9db9623a61f35b20610251ee4"
    },
    {
      "sourceBoardId": "227",
      "sourceBoardName": "immigration-monthly-statistics",
      "articleId": "327505",
      "articleTitle": "2017년 10월호 출입국외국인정책 통계월보",
      "publishedAt": "2017.11.17",
      "attachmentId": "277137",
      "attachmentName": "2.xls",
      "attachmentUrl": "https://www.immigration.go.kr/bbs/immigration/227/277137/download.do",
      "localPath": "data/raw/2017/2017-10/2.xls",
      "downloadedAt": "2026-03-26T08:59:23.487Z",
      "status": "downloaded",
      "checksum": "e0f295866a2bdfd9554c9e47ac634deb6f236c694664f010e9f9ea10030d3102"
    },
    {
      "sourceBoardId": "227",
      "sourceBoardName": "immigration-monthly-statistics",
      "articleId": "327501",
      "articleTitle": "2017년 9월호 출입국외국인정책 통계월보",
      "publishedAt": "2017.10.30",
      "attachmentId": "277127",
      "attachmentName": "2.xls",
      "attachmentUrl": "https://www.immigration.go.kr/bbs/immigration/227/277127/download.do",
      "localPath": "data/raw/2017/2017-09/2.xls",
      "downloadedAt": "2026-03-26T08:59:23.588Z",
      "status": "downloaded",
      "checksum": "8466b4e40ae3fc46e2d39b3ba7f7ff8cebeecfed427c567adf84c17995607249"
    },
    {
      "sourceBoardId": "227",
      "sourceBoardName": "immigration-monthly-statistics",
      "articleId": "327500",
      "articleTitle": "2017년 8월호 출입국외국인정책 통계월보",
      "publishedAt": "2017.09.27",
      "attachmentId": "277124",
      "attachmentName": "2.xls",
      "attachmentUrl": "https://www.immigration.go.kr/bbs/immigration/227/277124/download.do",
      "localPath": "data/raw/2017/2017-08/2.xls",
      "downloadedAt": "2026-03-26T08:59:23.693Z",
      "status": "downloaded",
      "checksum": "192c0bd043f729abd0845eece097da2d49db73c26a9c80ad3c2bdefd96499191"
    },
    {
      "sourceBoardId": "227",
      "sourceBoardName": "immigration-monthly-statistics",
      "articleId": "327499",
      "articleTitle": "2017년 7월호 출입국외국인정책 통계월보",
      "publishedAt": "2017.08.28",
      "attachmentId": "277121",
      "attachmentName": "2.xls",
      "attachmentUrl": "https://www.immigration.go.kr/bbs/immigration/227/277121/download.do",
      "localPath": "data/raw/2017/2017-07/2.xls",
      "downloadedAt": "2026-03-26T08:59:23.790Z",
      "status": "downloaded",
      "checksum": "f1db9f20f36c4eea3e9398d74dda8f55d5ac7467c9964763331922a215cbd912"
    },
    {
      "sourceBoardId": "227",
      "sourceBoardName": "immigration-monthly-statistics",
      "articleId": "327495",
      "articleTitle": "2017년 6월호 출입국외국인정책 통계월보",
      "publishedAt": "2017.07.21",
      "attachmentId": "277109",
      "attachmentName": "2.xlsx",
      "attachmentUrl": "https://www.immigration.go.kr/bbs/immigration/227/277109/download.do",
      "localPath": "data/raw/2017/2017-06/2.xlsx",
      "downloadedAt": "2026-03-26T08:59:25.522Z",
      "status": "downloaded",
      "checksum": "4735426d24745fac8407b57af6b2244af6850c935fa2a0bae7393bf8d4d33bab"
    },
    {
      "sourceBoardId": "227",
      "sourceBoardName": "immigration-monthly-statistics",
      "articleId": "327494",
      "articleTitle": "2017년 5월호 출입국외국인정책 통계월보",
      "publishedAt": "2017.06.28",
      "attachmentId": "277105",
      "attachmentName": "2.xlsx",
      "attachmentUrl": "https://www.immigration.go.kr/bbs/immigration/227/277105/download.do",
      "localPath": "data/raw/2017/2017-05/2.xlsx",
      "downloadedAt": "2026-03-26T08:59:25.656Z",
      "status": "downloaded",
      "checksum": "4fd5ac87502fbedf55a717e5710baaeec05c1def033ff1c3b551a1ec5f670820"
    },
    {
      "sourceBoardId": "227",
      "sourceBoardName": "immigration-monthly-statistics",
      "articleId": "327493",
      "articleTitle": "2017년 4월호 출입국외국인정책 통계월보",
      "publishedAt": "2017.05.25",
      "attachmentId": "277103",
      "attachmentName": "2.xls",
      "attachmentUrl": "https://www.immigration.go.kr/bbs/immigration/227/277103/download.do",
      "localPath": "data/raw/2017/2017-04/2.xls",
      "downloadedAt": "2026-03-26T08:59:25.790Z",
      "status": "downloaded",
      "checksum": "b950607d23c58a60f6ef1d6d30e28ced68c44deb8bebb62a7c54e4b424219e03"
    },
    {
      "sourceBoardId": "227",
      "sourceBoardName": "immigration-monthly-statistics",
      "articleId": "327489",
      "articleTitle": "2017년 3월호 출입국외국인정책 통계월보",
      "publishedAt": "2017.04.21",
      "attachmentId": "277092",
      "attachmentName": "2.xls",
      "attachmentUrl": "https://www.immigration.go.kr/bbs/immigration/227/277092/download.do",
      "localPath": "data/raw/2017/2017-03/2.xls",
      "downloadedAt": "2026-03-26T08:59:25.921Z",
      "status": "downloaded",
      "checksum": "f37a37057f54c954061d0b912a4fea64c5fac2e8c063cde9dbf4d2ee89443a53"
    },
    {
      "sourceBoardId": "227",
      "sourceBoardName": "immigration-monthly-statistics",
      "articleId": "327488",
      "articleTitle": "2017년 2월호 출입국외국인정책 통계월보",
      "publishedAt": "2017.03.24",
      "attachmentId": "277089",
      "attachmentName": "2.xlsx",
      "attachmentUrl": "https://www.immigration.go.kr/bbs/immigration/227/277089/download.do",
      "localPath": "data/raw/2017/2017-02/2.xlsx",
      "downloadedAt": "2026-03-26T08:59:26.039Z",
      "status": "downloaded",
      "checksum": "cf53fe2bed0e711fc01f2e11a5e52eb8f774f397545127de72cadecedbfb2996"
    },
    {
      "sourceBoardId": "227",
      "sourceBoardName": "immigration-monthly-statistics",
      "articleId": "327487",
      "articleTitle": "2017년 1월호 출입국외국인정책 통계월보",
      "publishedAt": "2017.02.24",
      "attachmentId": "277086",
      "attachmentName": "2.xls",
      "attachmentUrl": "https://www.immigration.go.kr/bbs/immigration/227/277086/download.do",
      "localPath": "data/raw/2017/2017-01/2.xls",
      "downloadedAt": "2026-03-26T08:59:26.152Z",
      "status": "downloaded",
      "checksum": "1f073b481f39ec8041707a0fd109c5148caf516cd81f970ae55d565a27f0263d"
    },
    {
      "sourceBoardId": "227",
      "sourceBoardName": "immigration-monthly-statistics",
      "articleId": "327485",
      "articleTitle": "2016년 12월호 출입국외국인정책 통계월보",
      "publishedAt": "2017.01.23",
      "attachmentId": "277082",
      "attachmentName": "2.xls",
      "attachmentUrl": "https://www.immigration.go.kr/bbs/immigration/227/277082/download.do",
      "localPath": "data/raw/2016/2016-12/2.xls",
      "downloadedAt": "2026-03-26T08:59:26.258Z",
      "status": "downloaded",
      "checksum": "49d2ed7535eb19040fb20bdb50fa22f10167bd2c78fd1ecebe8003a2f5704238"
    },
    {
      "sourceBoardId": "227",
      "sourceBoardName": "immigration-monthly-statistics",
      "articleId": "327481",
      "articleTitle": "2016년 11월호 출입국외국인정책 통계월보",
      "publishedAt": "2016.12.23",
      "attachmentId": "277071",
      "attachmentName": "2.xls",
      "attachmentUrl": "https://www.immigration.go.kr/bbs/immigration/227/277071/download.do",
      "localPath": "data/raw/2016/2016-11/2.xls",
      "downloadedAt": "2026-03-26T08:59:26.373Z",
      "status": "downloaded",
      "checksum": "6309b200b8c410d29cd258cc9061fdcc78ea6960c5749433d912656426dadb03"
    },
    {
      "sourceBoardId": "227",
      "sourceBoardName": "immigration-monthly-statistics",
      "articleId": "327480",
      "articleTitle": "2016년 10월호 출입국외국인정책 통계월보",
      "publishedAt": "2016.11.24",
      "attachmentId": "277067",
      "attachmentName": "2.xls",
      "attachmentUrl": "https://www.immigration.go.kr/bbs/immigration/227/277067/download.do",
      "localPath": "data/raw/2016/2016-10/2.xls",
      "downloadedAt": "2026-03-26T08:59:26.494Z",
      "status": "downloaded",
      "checksum": "81d48b7052c23ef3d48adaab154c6a2a44af5ba6a81961cc72fe70ae68faed18"
    },
    {
      "sourceBoardId": "227",
      "sourceBoardName": "immigration-monthly-statistics",
      "articleId": "327479",
      "articleTitle": "2016년 9월호 출입국외국인정책 통계월보",
      "publishedAt": "2016.10.26",
      "attachmentId": "277064",
      "attachmentName": "2.xls",
      "attachmentUrl": "https://www.immigration.go.kr/bbs/immigration/227/277064/download.do",
      "localPath": "data/raw/2016/2016-09/2.xls",
      "downloadedAt": "2026-03-26T08:59:26.594Z",
      "status": "downloaded",
      "checksum": "87cbeedc85fc6a415eb72873663f7476c0215d049ae58bbc2b7e53cf1ace4b7d"
    },
    {
      "sourceBoardId": "227",
      "sourceBoardName": "immigration-monthly-statistics",
      "articleId": "327475",
      "articleTitle": "2016년 8월호 통계월보",
      "publishedAt": "2016.09.27",
      "attachmentId": "277053",
      "attachmentName": "2.xls",
      "attachmentUrl": "https://www.immigration.go.kr/bbs/immigration/227/277053/download.do",
      "localPath": "data/raw/2016/2016-08/2.xls",
      "downloadedAt": "2026-03-26T08:59:26.711Z",
      "status": "downloaded",
      "checksum": "21f1b1418333cd4fb3fee713e81bedf9b756102143fa96079099f60dc4062e0a"
    },
    {
      "sourceBoardId": "227",
      "sourceBoardName": "immigration-monthly-statistics",
      "articleId": "327474",
      "articleTitle": "2016년 7월호 통계월보",
      "publishedAt": "2016.08.30",
      "attachmentId": "277051",
      "attachmentName": "2.xls",
      "attachmentUrl": "https://www.immigration.go.kr/bbs/immigration/227/277051/download.do",
      "localPath": "data/raw/2016/2016-07/2.xls",
      "downloadedAt": "2026-03-26T08:59:26.834Z",
      "status": "downloaded",
      "checksum": "c149eb16f9c980dcb7d3f57c6a107cea371f2c2d7a6f5843ef9724719286081b"
    },
    {
      "sourceBoardId": "227",
      "sourceBoardName": "immigration-monthly-statistics",
      "articleId": "327470",
      "articleTitle": "2016년도 6월호 통계월보",
      "publishedAt": "2016.07.27",
      "attachmentId": "277040",
      "attachmentName": "2.xls",
      "attachmentUrl": "https://www.immigration.go.kr/bbs/immigration/227/277040/download.do",
      "localPath": "data/raw/2016/2016-07/2.xls",
      "downloadedAt": "2026-03-26T08:59:26.949Z",
      "status": "downloaded",
      "checksum": "4847e4a22364d56d62bad940f2619b24ca25effa8b0bb8b9119d3e767f958ba0"
    },
    {
      "sourceBoardId": "227",
      "sourceBoardName": "immigration-monthly-statistics",
      "articleId": "327469",
      "articleTitle": "2016년도 5월호 통계월보",
      "publishedAt": "2016.06.28",
      "attachmentId": "277037",
      "attachmentName": "2.xls",
      "attachmentUrl": "https://www.immigration.go.kr/bbs/immigration/227/277037/download.do",
      "localPath": "data/raw/2016/2016-06/2.xls",
      "downloadedAt": "2026-03-26T08:59:27.047Z",
      "status": "downloaded",
      "checksum": "3e98b04d8daab5ae4185adb1c194db5fe3fb129c0b420004ca8ac3ac713e895c"
    },
    {
      "sourceBoardId": "227",
      "sourceBoardName": "immigration-monthly-statistics",
      "articleId": "327468",
      "articleTitle": "2016년도 4월호 통계월보",
      "publishedAt": "2016.05.27",
      "attachmentId": "277034",
      "attachmentName": "2.xls",
      "attachmentUrl": "https://www.immigration.go.kr/bbs/immigration/227/277034/download.do",
      "localPath": "data/raw/2016/2016-05/2.xls",
      "downloadedAt": "2026-03-26T08:59:27.162Z",
      "status": "downloaded",
      "checksum": "58655ecd5ed22f3d149f348253bc546c9121cf1e09706fd9e7e0b6a15c08cce4"
    },
    {
      "sourceBoardId": "227",
      "sourceBoardName": "immigration-monthly-statistics",
      "articleId": "327464",
      "articleTitle": "2016년도 3월호 통계월보",
      "publishedAt": "2016.04.28",
      "attachmentId": "277023",
      "attachmentName": "2.xls",
      "attachmentUrl": "https://www.immigration.go.kr/bbs/immigration/227/277023/download.do",
      "localPath": "data/raw/2016/2016-04/2.xls",
      "downloadedAt": "2026-03-26T08:59:27.277Z",
      "status": "downloaded",
      "checksum": "5d313cb121ed46be3d72d0c155783236c8e7d18f69d01f26e94b0e7f7bdc5721"
    },
    {
      "sourceBoardId": "227",
      "sourceBoardName": "immigration-monthly-statistics",
      "articleId": "327463",
      "articleTitle": "2016년도 2월호 통계월보",
      "publishedAt": "2016.03.25",
      "attachmentId": "277019",
      "attachmentName": "2.xlsx",
      "attachmentUrl": "https://www.immigration.go.kr/bbs/immigration/227/277019/download.do",
      "localPath": "data/raw/2016/2016-03/2.xlsx",
      "downloadedAt": "2026-03-26T08:59:27.362Z",
      "status": "downloaded",
      "checksum": "bfdd6b8e8e9ac1e3d62bf75f7683cdd32495592182628a6adc5acb0cea49918b"
    },
    {
      "sourceBoardId": "227",
      "sourceBoardName": "immigration-monthly-statistics",
      "articleId": "327462",
      "articleTitle": "2016년도 1월호 통계월보",
      "publishedAt": "2016.02.29",
      "attachmentId": "277017",
      "attachmentName": "2.xls",
      "attachmentUrl": "https://www.immigration.go.kr/bbs/immigration/227/277017/download.do",
      "localPath": "data/raw/2016/2016-02/2.xls",
      "downloadedAt": "2026-03-26T08:59:27.459Z",
      "status": "downloaded",
      "checksum": "6a40e662bde01a9ce6de00452542d64968c8c7d256385d8aca7fecf7ac1dc249"
    },
    {
      "sourceBoardId": "227",
      "sourceBoardName": "immigration-monthly-statistics",
      "articleId": "327458",
      "articleTitle": "2015년 12월호 통계월보",
      "publishedAt": "2016.01.27",
      "attachmentId": "277005",
      "attachmentName": "2.xls",
      "attachmentUrl": "https://www.immigration.go.kr/bbs/immigration/227/277005/download.do",
      "localPath": "data/raw/2015/2015-12/2.xls",
      "downloadedAt": "2026-03-26T08:59:27.560Z",
      "status": "downloaded",
      "checksum": "ec8089424e60e91638525da0f9e62365378c213310cd81d90a98c261d4ed69dc"
    },
    {
      "sourceBoardId": "227",
      "sourceBoardName": "immigration-monthly-statistics",
      "articleId": "327457",
      "articleTitle": "2015년 11월호 통계월보",
      "publishedAt": "2015.12.23",
      "attachmentId": "277003",
      "attachmentName": "2.xls",
      "attachmentUrl": "https://www.immigration.go.kr/bbs/immigration/227/277003/download.do",
      "localPath": "data/raw/2015/2015-11/2.xls",
      "downloadedAt": "2026-03-26T08:59:27.660Z",
      "status": "downloaded",
      "checksum": "080b68cf05e304149d4079eda58429bb3f6d1d50aa9d7fc71c6bf5cdea99bcff"
    },
    {
      "sourceBoardId": "227",
      "sourceBoardName": "immigration-monthly-statistics",
      "articleId": "327456",
      "articleTitle": "2015년 10월호 통계월보",
      "publishedAt": "2015.11.26",
      "attachmentId": "276999",
      "attachmentName": "2.xls",
      "attachmentUrl": "https://www.immigration.go.kr/bbs/immigration/227/276999/download.do",
      "localPath": "data/raw/2015/2015-10/2.xls",
      "downloadedAt": "2026-03-26T08:59:27.779Z",
      "status": "downloaded",
      "checksum": "50c08e03c97b6773d2ddbbe530f880cf0349c9ba8b6683eedbc2ee831e0d9148"
    },
    {
      "sourceBoardId": "227",
      "sourceBoardName": "immigration-monthly-statistics",
      "articleId": "327451",
      "articleTitle": "2015년 8월호 통계월보",
      "publishedAt": "2015.09.25",
      "attachmentId": "276985",
      "attachmentName": "2.xls",
      "attachmentUrl": "https://www.immigration.go.kr/bbs/immigration/227/276985/download.do",
      "localPath": "data/raw/2015/2015-08/2.xls",
      "downloadedAt": "2026-03-26T08:59:27.902Z",
      "status": "downloaded",
      "checksum": "4e439d1ac235f8a40f9de5dbbb72dd77d0ae4bfb39ee20c44b1b436d99f21571"
    },
    {
      "sourceBoardId": "227",
      "sourceBoardName": "immigration-monthly-statistics",
      "articleId": "327450",
      "articleTitle": "2015년 7월호 통계월보",
      "publishedAt": "2015.08.25",
      "attachmentId": "276983",
      "attachmentName": "2.xls",
      "attachmentUrl": "https://www.immigration.go.kr/bbs/immigration/227/276983/download.do",
      "localPath": "data/raw/2015/2015-07/2.xls",
      "downloadedAt": "2026-03-26T08:59:28.005Z",
      "status": "downloaded",
      "checksum": "b91f5fe34110eb541708b23d180f8ebaf0b4710f7acd385ec1fff38865138797"
    },
    {
      "sourceBoardId": "227",
      "sourceBoardName": "immigration-monthly-statistics",
      "articleId": "327446",
      "articleTitle": "2015년 6월호 통계월보",
      "publishedAt": "2015.07.23",
      "attachmentId": "276971",
      "attachmentName": "2.xls",
      "attachmentUrl": "https://www.immigration.go.kr/bbs/immigration/227/276971/download.do",
      "localPath": "data/raw/2015/2015-06/2.xls",
      "downloadedAt": "2026-03-26T08:59:28.111Z",
      "status": "downloaded",
      "checksum": "97f697d27ec52302d5a52b8b4f51a398d0ee62a4729e1f4d8c8c3e84a3725b8c"
    },
    {
      "sourceBoardId": "227",
      "sourceBoardName": "immigration-monthly-statistics",
      "articleId": "327445",
      "articleTitle": "2015년 5월호 통계월보",
      "publishedAt": "2015.06.25",
      "attachmentId": "276969",
      "attachmentName": "2.xls",
      "attachmentUrl": "https://www.immigration.go.kr/bbs/immigration/227/276969/download.do",
      "localPath": "data/raw/2015/2015-05/2.xls",
      "downloadedAt": "2026-03-26T08:59:28.201Z",
      "status": "downloaded",
      "checksum": "10c36e7ab83887dfae0409d9081fbf2cdd5cf057faf63eeafd775c352623844d"
    },
    {
      "sourceBoardId": "227",
      "sourceBoardName": "immigration-monthly-statistics",
      "articleId": "327444",
      "articleTitle": "2015년 4월호 통계월보",
      "publishedAt": "2015.05.26",
      "attachmentId": "276965",
      "attachmentName": "2.xlsx",
      "attachmentUrl": "https://www.immigration.go.kr/bbs/immigration/227/276965/download.do",
      "localPath": "data/raw/2015/2015-04/2.xlsx",
      "downloadedAt": "2026-03-26T08:59:28.303Z",
      "status": "downloaded",
      "checksum": "6cb058c9ab3e49b93642f1f19ac6a8c201a97bd9a22a12c2f61d21bcffaa0bb5"
    },
    {
      "sourceBoardId": "227",
      "sourceBoardName": "immigration-monthly-statistics",
      "articleId": "327440",
      "articleTitle": "2015년 3월호 통계월보",
      "publishedAt": "2015.04.24",
      "attachmentId": "276954",
      "attachmentName": "2.xlsx",
      "attachmentUrl": "https://www.immigration.go.kr/bbs/immigration/227/276954/download.do",
      "localPath": "data/raw/2015/2015-03/2.xlsx",
      "downloadedAt": "2026-03-26T08:59:28.389Z",
      "status": "downloaded",
      "checksum": "52af41ee82661c994d753aeafb0d28e1dbdfd86d59853613a0096cb7c307cb29"
    },
    {
      "sourceBoardId": "227",
      "sourceBoardName": "immigration-monthly-statistics",
      "articleId": "327439",
      "articleTitle": "2015년 2월호 통계월보",
      "publishedAt": "2015.03.25",
      "attachmentId": "276951",
      "attachmentName": "2.xlsx",
      "attachmentUrl": "https://www.immigration.go.kr/bbs/immigration/227/276951/download.do",
      "localPath": "data/raw/2015/2015-02/2.xlsx",
      "downloadedAt": "2026-03-26T08:59:28.491Z",
      "status": "downloaded",
      "checksum": "1d083527c12de669cf07783e62582fe0e2d3c65261d30586409fcf5074199a41"
    },
    {
      "sourceBoardId": "227",
      "sourceBoardName": "immigration-monthly-statistics",
      "articleId": "327438",
      "articleTitle": "2015년 1월호 통계월보",
      "publishedAt": "2015.02.25",
      "attachmentId": "276949",
      "attachmentName": "2.xlsx",
      "attachmentUrl": "https://www.immigration.go.kr/bbs/immigration/227/276949/download.do",
      "localPath": "data/raw/2015/2015-01/2.xlsx",
      "downloadedAt": "2026-03-26T08:59:28.602Z",
      "status": "downloaded",
      "checksum": "51a4ab76385cd3d575ea9f6957d98561ea9cd28fc50b47926830cec507965ffe"
    },
    {
      "sourceBoardId": "227",
      "sourceBoardName": "immigration-monthly-statistics",
      "articleId": "327434",
      "articleTitle": "통계월보 2014년 12월호",
      "publishedAt": "2015.01.26",
      "attachmentId": "276938",
      "attachmentName": "2.xlsx",
      "attachmentUrl": "https://www.immigration.go.kr/bbs/immigration/227/276938/download.do",
      "localPath": "data/raw/2014/2014-12/2.xlsx",
      "downloadedAt": "2026-03-26T08:59:28.722Z",
      "status": "downloaded",
      "checksum": "17adf7849e7170551c586130a5a63c5f2a44618394024659d1e3730bdfc475f3"
    },
    {
      "sourceBoardId": "227",
      "sourceBoardName": "immigration-monthly-statistics",
      "articleId": "327433",
      "articleTitle": "통계월보 2014년 11월호",
      "publishedAt": "2014.12.19",
      "attachmentId": "276934",
      "attachmentName": "2.xlsx",
      "attachmentUrl": "https://www.immigration.go.kr/bbs/immigration/227/276934/download.do",
      "localPath": "data/raw/2014/2014-11/2.xlsx",
      "downloadedAt": "2026-03-26T08:59:28.834Z",
      "status": "downloaded",
      "checksum": "13220a571a4a121e96999de3889614ea7d04e77ec6aca588150dfe8c9fd6d8f2"
    },
    {
      "sourceBoardId": "227",
      "sourceBoardName": "immigration-monthly-statistics",
      "articleId": "327432",
      "articleTitle": "통계월보 2014년 10월호",
      "publishedAt": "2014.11.20",
      "attachmentId": "276932",
      "attachmentName": "2.xlsx",
      "attachmentUrl": "https://www.immigration.go.kr/bbs/immigration/227/276932/download.do",
      "localPath": "data/raw/2014/2014-10/2.xlsx",
      "downloadedAt": "2026-03-26T08:59:28.949Z",
      "status": "downloaded",
      "checksum": "331d6ec2c45628f4018a4bd8c6e903c747e6190d7535d3f3e54035865b113cc8"
    },
    {
      "sourceBoardId": "227",
      "sourceBoardName": "immigration-monthly-statistics",
      "articleId": "327428",
      "articleTitle": "통계월보 2014년 9월호",
      "publishedAt": "2014.10.26",
      "attachmentId": "276921",
      "attachmentName": "2.xlsx",
      "attachmentUrl": "https://www.immigration.go.kr/bbs/immigration/227/276921/download.do",
      "localPath": "data/raw/2014/2014-09/2.xlsx",
      "downloadedAt": "2026-03-26T08:59:29.071Z",
      "status": "downloaded",
      "checksum": "7945e4fce12fda08948af9b85ea047d2faee113088f3fae3ce799c0cad1a74ea"
    },
    {
      "sourceBoardId": "227",
      "sourceBoardName": "immigration-monthly-statistics",
      "articleId": "327427",
      "articleTitle": "통계월보 2014년 8월호",
      "publishedAt": "2014.09.18",
      "attachmentId": "276918",
      "attachmentName": "2.xlsx",
      "attachmentUrl": "https://www.immigration.go.kr/bbs/immigration/227/276918/download.do",
      "localPath": "data/raw/2014/2014-08/2.xlsx",
      "downloadedAt": "2026-03-26T08:59:29.211Z",
      "status": "downloaded",
      "checksum": "e8ff4d394aed29b2b290a6c91e146da1a86276a9540ecf48b86a3fd133827c39"
    },
    {
      "sourceBoardId": "227",
      "sourceBoardName": "immigration-monthly-statistics",
      "articleId": "327426",
      "articleTitle": "통계월보 2014년 7월호",
      "publishedAt": "2014.08.20",
      "attachmentId": "276912",
      "attachmentName": "2.xlsx",
      "attachmentUrl": "https://www.immigration.go.kr/bbs/immigration/227/276912/download.do",
      "localPath": "data/raw/2014/2014-07/2.xlsx",
      "downloadedAt": "2026-03-26T08:59:29.348Z",
      "status": "downloaded",
      "checksum": "36d4b23a8e30a0c0d08bd6a62a116abe413d868136e4aca5f55d0c226e80c95e"
    },
    {
      "sourceBoardId": "227",
      "sourceBoardName": "immigration-monthly-statistics",
      "articleId": "327422",
      "articleTitle": "통계월보 2014년 6월호",
      "publishedAt": "2014.07.18",
      "attachmentId": "276900",
      "attachmentName": "2.xlsx",
      "attachmentUrl": "https://www.immigration.go.kr/bbs/immigration/227/276900/download.do",
      "localPath": "data/raw/2014/2014-06/2.xlsx",
      "downloadedAt": "2026-03-26T08:59:29.475Z",
      "status": "downloaded",
      "checksum": "6b90c8d6af16378e4494c0146df2d4215aad60c336081a3eb9e8ab01d813569c"
    },
    {
      "sourceBoardId": "227",
      "sourceBoardName": "immigration-monthly-statistics",
      "articleId": "327421",
      "articleTitle": "통계월보 2014년 5월호",
      "publishedAt": "2014.06.18",
      "attachmentId": "276898",
      "attachmentName": "2.xlsx",
      "attachmentUrl": "https://www.immigration.go.kr/bbs/immigration/227/276898/download.do",
      "localPath": "data/raw/2014/2014-05/2.xlsx",
      "downloadedAt": "2026-03-26T08:59:29.591Z",
      "status": "downloaded",
      "checksum": "051086b32bea8dcf94913a02cd84aaba9ef4537c7df174ad4d05caa08a5b3f41"
    },
    {
      "sourceBoardId": "227",
      "sourceBoardName": "immigration-monthly-statistics",
      "articleId": "327420",
      "articleTitle": "통계월보 2014년 4월호",
      "publishedAt": "2014.05.20",
      "attachmentId": "276894",
      "attachmentName": "2.xlsx",
      "attachmentUrl": "https://www.immigration.go.kr/bbs/immigration/227/276894/download.do",
      "localPath": "data/raw/2014/2014-04/2.xlsx",
      "downloadedAt": "2026-03-26T08:59:29.705Z",
      "status": "downloaded",
      "checksum": "328e49c9b49bcfe6426ae405dbc100dd79d9c9f0e404c4f350cdbad5d969c733"
    },
    {
      "sourceBoardId": "227",
      "sourceBoardName": "immigration-monthly-statistics",
      "articleId": "327416",
      "articleTitle": "통계월보 2014년 3월호",
      "publishedAt": "2014.04.18",
      "attachmentId": "276883",
      "attachmentName": "2.xlsx",
      "attachmentUrl": "https://www.immigration.go.kr/bbs/immigration/227/276883/download.do",
      "localPath": "data/raw/2014/2014-03/2.xlsx",
      "downloadedAt": "2026-03-26T08:59:29.839Z",
      "status": "downloaded",
      "checksum": "56be6f08b65daf4596d16c3367a478ec9eca26bc0cb3ee85493d933c1d74d96b"
    },
    {
      "sourceBoardId": "227",
      "sourceBoardName": "immigration-monthly-statistics",
      "articleId": "327415",
      "articleTitle": "통계월보 2014년 2월호",
      "publishedAt": "2014.03.20",
      "attachmentId": "276881",
      "attachmentName": "2.xlsx",
      "attachmentUrl": "https://www.immigration.go.kr/bbs/immigration/227/276881/download.do",
      "localPath": "data/raw/2014/2014-02/2.xlsx",
      "downloadedAt": "2026-03-26T08:59:29.946Z",
      "status": "downloaded",
      "checksum": "8111595c2d285873037ebe3d8c5bf195a49288e7b53cebb33fdb265d25b7b7cc"
    },
    {
      "sourceBoardId": "227",
      "sourceBoardName": "immigration-monthly-statistics",
      "articleId": "327414",
      "articleTitle": "통계월보 2014년 1월호",
      "publishedAt": "2014.02.19",
      "attachmentId": "276877",
      "attachmentName": "2.xlsx",
      "attachmentUrl": "https://www.immigration.go.kr/bbs/immigration/227/276877/download.do",
      "localPath": "data/raw/2014/2014-01/2.xlsx",
      "downloadedAt": "2026-03-26T08:59:30.043Z",
      "status": "downloaded",
      "checksum": "1e21cb867f2eae58bf009e37f75f3a525545ba3100ca3698ce550df421791eef"
    },
    {
      "sourceBoardId": "227",
      "sourceBoardName": "immigration-monthly-statistics",
      "articleId": "327410",
      "articleTitle": "2013년 12월 통계월보",
      "publishedAt": "2014.01.20",
      "attachmentId": "276866",
      "attachmentName": "2.xlsx",
      "attachmentUrl": "https://www.immigration.go.kr/bbs/immigration/227/276866/download.do",
      "localPath": "data/raw/2013/2013-12/2.xlsx",
      "downloadedAt": "2026-03-26T08:59:30.167Z",
      "status": "downloaded",
      "checksum": "be7d9e95d392a7a069f1118117128d775fd3343ba623ae4d1f2edccf2cdfcf8b"
    },
    {
      "sourceBoardId": "227",
      "sourceBoardName": "immigration-monthly-statistics",
      "articleId": "327408",
      "articleTitle": "2013년 10월 통계월보",
      "publishedAt": "2013.11.20",
      "attachmentId": "276861",
      "attachmentName": "2.xlsx",
      "attachmentUrl": "https://www.immigration.go.kr/bbs/immigration/227/276861/download.do",
      "localPath": "data/raw/2013/2013-10/2.xlsx",
      "downloadedAt": "2026-03-26T08:59:30.275Z",
      "status": "downloaded",
      "checksum": "098f05da15d595f441bbb868c62fbf961cd669153ac09aeaac1bfee65f1146b5"
    },
    {
      "sourceBoardId": "227",
      "sourceBoardName": "immigration-monthly-statistics",
      "articleId": "327404",
      "articleTitle": "2013년 9월 통계월보",
      "publishedAt": "2013.10.22",
      "attachmentId": "276849",
      "attachmentName": "2.xlsx",
      "attachmentUrl": "https://www.immigration.go.kr/bbs/immigration/227/276849/download.do",
      "localPath": "data/raw/2013/2013-09/2.xlsx",
      "downloadedAt": "2026-03-26T08:59:30.400Z",
      "status": "downloaded",
      "checksum": "511c79dfff73c51d4f949ba5ded1c1c168b8fc92b0e3ad0d19764f05be13cce1"
    },
    {
      "sourceBoardId": "227",
      "sourceBoardName": "immigration-monthly-statistics",
      "articleId": "327403",
      "articleTitle": "2013년 8월 통계월보",
      "publishedAt": "2013.09.24",
      "attachmentId": "276845",
      "attachmentName": "2.xlsx",
      "attachmentUrl": "https://www.immigration.go.kr/bbs/immigration/227/276845/download.do",
      "localPath": "data/raw/2013/2013-08/2.xlsx",
      "downloadedAt": "2026-03-26T08:59:30.523Z",
      "status": "downloaded",
      "checksum": "96578a53d6aba0f2ea7b0ca604354fb4ed0e01dff0db7e678032a4d2f9c23be2"
    },
    {
      "sourceBoardId": "227",
      "sourceBoardName": "immigration-monthly-statistics",
      "articleId": "327402",
      "articleTitle": "2013년 7월 통계월보",
      "publishedAt": "2013.08.20",
      "attachmentId": "276842",
      "attachmentName": "2.xlsx",
      "attachmentUrl": "https://www.immigration.go.kr/bbs/immigration/227/276842/download.do",
      "localPath": "data/raw/2013/2013-07/2.xlsx",
      "downloadedAt": "2026-03-26T08:59:30.636Z",
      "status": "downloaded",
      "checksum": "a75494fca97536e15eaf9a451f40b19813d31630ba093f0c272851f67768a36f"
    },
    {
      "sourceBoardId": "227",
      "sourceBoardName": "immigration-monthly-statistics",
      "articleId": "327342",
      "articleTitle": "2010년 5월 통계월보",
      "publishedAt": "2010.06.21",
      "attachmentId": "276699",
      "attachmentName": "2.xlsx",
      "attachmentUrl": "https://www.immigration.go.kr/bbs/immigration/227/276699/download.do",
      "localPath": "data/raw/2010/2010-05/2.xlsx",
      "downloadedAt": "2026-03-26T08:59:30.723Z",
      "status": "downloaded",
      "checksum": "3be0a209118925c0223893ff2f4cd71d045a5dfc204fae658c06decbcd4e3fb2"
    },
    {
      "sourceBoardId": "227",
      "sourceBoardName": "immigration-monthly-statistics",
      "articleId": "327314",
      "articleTitle": "2008년 8월 통계월보",
      "publishedAt": "2008.09.24",
      "attachmentId": "276643",
      "attachmentName": "첨부 1-1. 국적 및 체류자격별 외국인입국자(누계)_2008년08월.xls",
      "attachmentUrl": "https://www.immigration.go.kr/bbs/immigration/227/276643/download.do",
      "localPath": "data/raw/2008/2008-08/첨부 1-1. 국적 및 체류자격별 외국인입국자(누계)_2008년08월.xls",
      "downloadedAt": "2026-03-26T08:59:30.820Z",
      "status": "downloaded",
      "checksum": "bec5065886cbaf327c3cffaaa36fb84bacdbdc65d2ed4914a8ecc7b6164d8617"
    },
    {
      "sourceBoardId": "227",
      "sourceBoardName": "immigration-monthly-statistics",
      "articleId": "327313",
      "articleTitle": "2008년 7월 통계월보",
      "publishedAt": "2008.08.27",
      "attachmentId": "276635",
      "attachmentName": "1-1. 국적 및 체류자격별 외국인입국자(누계)_2008년07월.xls",
      "attachmentUrl": "https://www.immigration.go.kr/bbs/immigration/227/276635/download.do",
      "localPath": "data/raw/2008/2008-07/1-1. 국적 및 체류자격별 외국인입국자(누계)_2008년07월.xls",
      "downloadedAt": "2026-03-26T08:59:30.924Z",
      "status": "downloaded",
      "checksum": "141a139ce55938e79cf0291fbdeeeab92932aa8f04f9a1e4d4cc8b5b6877248a"
    },
    {
      "sourceBoardId": "227",
      "sourceBoardName": "immigration-monthly-statistics",
      "articleId": "327312",
      "articleTitle": "2008년 6월 통계월보",
      "publishedAt": "2008.07.23",
      "attachmentId": "276627",
      "attachmentName": "1-1. 국적 및 체류자격별 외국인입국자(누계)_2008년06월.xls",
      "attachmentUrl": "https://www.immigration.go.kr/bbs/immigration/227/276627/download.do",
      "localPath": "data/raw/2008/2008-06/1-1. 국적 및 체류자격별 외국인입국자(누계)_2008년06월.xls",
      "downloadedAt": "2026-03-26T08:59:31.019Z",
      "status": "downloaded",
      "checksum": "9e711f5ba9a0e3a7f8822ddf2bb0c6d734bda328e59b86365f3cf3aeb0f29a33"
    },
    {
      "sourceBoardId": "227",
      "sourceBoardName": "immigration-monthly-statistics",
      "articleId": "327311",
      "articleTitle": "2008년 5월 통계월보",
      "publishedAt": "2008.06.20",
      "attachmentId": "276619",
      "attachmentName": "1-1. 국적 및 체류자격별 외국인입국자(누계)_2008년05월.xls",
      "attachmentUrl": "https://www.immigration.go.kr/bbs/immigration/227/276619/download.do",
      "localPath": "data/raw/2008/2008-05/1-1. 국적 및 체류자격별 외국인입국자(누계)_2008년05월.xls",
      "downloadedAt": "2026-03-26T08:59:31.115Z",
      "status": "downloaded",
      "checksum": "6092e4484d45f8cf381b4d59469eb4a1ee2eb5e82acc52eb46fb54f73edda84d"
    },
    {
      "sourceBoardId": "227",
      "sourceBoardName": "immigration-monthly-statistics",
      "articleId": "327310",
      "articleTitle": "2008년 4월 통계월보",
      "publishedAt": "2008.05.21",
      "attachmentId": "276611",
      "attachmentName": "1-1. 국적 및 체류자격별 외국인입국자(누계)_08년04월.xls",
      "attachmentUrl": "https://www.immigration.go.kr/bbs/immigration/227/276611/download.do",
      "localPath": "data/raw/2008/2008-04/1-1. 국적 및 체류자격별 외국인입국자(누계)_08년04월.xls",
      "downloadedAt": "2026-03-26T08:59:31.233Z",
      "status": "downloaded",
      "checksum": "0bed33e20cf4181987b24a762f26edbdf69b7ac84b19612500ec852df88c3f19"
    },
    {
      "sourceBoardId": "227",
      "sourceBoardName": "immigration-monthly-statistics",
      "articleId": "327309",
      "articleTitle": "2008년 3월 통계월보",
      "publishedAt": "2008.04.23",
      "attachmentId": "276606",
      "attachmentName": "첨부 1-1. 국적 및 체류자격별 외국인입국자(누계)_2008년3월.xls",
      "attachmentUrl": "https://www.immigration.go.kr/bbs/immigration/227/276606/download.do",
      "localPath": "data/raw/2008/2008-03/첨부 1-1. 국적 및 체류자격별 외국인입국자(누계)_2008년3월.xls",
      "downloadedAt": "2026-03-26T08:59:31.335Z",
      "status": "downloaded",
      "checksum": "2db247e4416a81c631fb3b21d3e1547c56c49bc80869b493fdd7097bdc1af12b"
    },
    {
      "sourceBoardId": "227",
      "sourceBoardName": "immigration-monthly-statistics",
      "articleId": "327306",
      "articleTitle": "2008년 2월 통계월보",
      "publishedAt": "2008.03.20",
      "attachmentId": "276598",
      "attachmentName": "첨부 1-1. 국적 및 체류자격별 외국인입국자(누계)_2008년2월.xls",
      "attachmentUrl": "https://www.immigration.go.kr/bbs/immigration/227/276598/download.do",
      "localPath": "data/raw/2008/2008-02/첨부 1-1. 국적 및 체류자격별 외국인입국자(누계)_2008년2월.xls",
      "downloadedAt": "2026-03-26T08:59:31.440Z",
      "status": "downloaded",
      "checksum": "28c2566aae730b5c9a97eff74f1e71cb886f04ab6db692b1d9a3ea9594f246e8"
    },
    {
      "sourceBoardId": "227",
      "sourceBoardName": "immigration-monthly-statistics",
      "articleId": "327303",
      "articleTitle": "2008년 1월 통계월보",
      "publishedAt": "2008.02.26",
      "attachmentId": "276590",
      "attachmentName": "첨부 1-1. 국적 및 체류자격별 외국인입국자(누계)_2008년1월.xls",
      "attachmentUrl": "https://www.immigration.go.kr/bbs/immigration/227/276590/download.do",
      "localPath": "data/raw/2008/2008-01/첨부 1-1. 국적 및 체류자격별 외국인입국자(누계)_2008년1월.xls",
      "downloadedAt": "2026-03-26T08:59:31.529Z",
      "status": "downloaded",
      "checksum": "2339e53448a0106e959d3159e9773f0729df5a8ca0c26ff18135315e6e04448b"
    },
    {
      "sourceBoardId": "227",
      "sourceBoardName": "immigration-monthly-statistics",
      "articleId": "605615",
      "articleTitle": "2026년 3월 출입국외국인정책 통계월보",
      "publishedAt": "2026.04.17",
      "attachmentId": "493612",
      "attachmentName": "1.2. 외국인입국자(3월).xlsx",
      "attachmentUrl": "https://www.immigration.go.kr/bbs/immigration/227/493612/download.do",
      "localPath": "data/raw/2026/2026-03/1.2. 외국인입국자(3월).xlsx",
      "downloadedAt": "2026-04-20T00:54:49.538Z",
      "status": "downloaded",
      "checksum": "529a82ab09b83568b6810f07c17fc94c7d6bafd36f5adaf8f59edff3a13e4afe"
    },
    {
      "sourceBoardId": "227",
      "sourceBoardName": "immigration-monthly-statistics",
      "articleId": "606790",
      "articleTitle": "2026년 4월 출입국외국인정책 통계월보",
      "publishedAt": "2026.05.21",
      "attachmentId": "495046",
      "attachmentName": "1.2. 외국인입국자(4월).xlsx",
      "attachmentUrl": "https://www.immigration.go.kr/bbs/immigration/227/495046/download.do",
      "localPath": "data/raw/2026/2026-04/1.2. 외국인입국자(4월).xlsx",
      "downloadedAt": "2026-05-27T02:00:56.922Z",
      "status": "downloaded",
      "checksum": "845bd2290b958ad83ffba0f906ef1b66ec2ba28be6abf89e9086073ba4550263"
    },
    {
      "sourceBoardId": "227",
      "sourceBoardName": "immigration-monthly-statistics",
      "articleId": "607714",
      "articleTitle": "2026년 5월 출입국외국인정책 통계월보",
      "publishedAt": "2026.06.22",
      "attachmentId": "496113",
      "attachmentName": "1.2. 외국인입국자(5월).xlsx",
      "attachmentUrl": "https://www.immigration.go.kr/bbs/immigration/227/496113/download.do",
      "localPath": "data/raw/2026/2026-05/1.2. 외국인입국자(5월).xlsx",
      "downloadedAt": "2026-06-24T00:58:44.327Z",
      "status": "downloaded",
      "checksum": "3c500fec38969b2d5988e5ac9aad1a7c773b524bfd734064e8fc5bb647f779c2"
    },
    {
      "sourceBoardId": "227",
      "sourceBoardName": "immigration-monthly-statistics",
      "articleId": "607714",
      "articleTitle": "2026년 5월 출입국외국인정책 통계월보",
      "publishedAt": "2026.06.22",
      "attachmentId": "496114",
      "attachmentName": "1.3. 체류외국인 원본 통계표(5월).xlsx",
      "attachmentUrl": "https://www.immigration.go.kr/bbs/immigration/227/496114/download.do",
      "localPath": "data/raw/2026/2026-05/1.3. 체류외국인 원본 통계표(5월).xlsx",
      "downloadedAt": "2026-06-24T01:08:30.446Z",
      "status": "downloaded",
      "checksum": "c9799dadf68cfac2e419b31ec6f4e3a30a6c9fed38c6696015c37e736fef361f"
    },
    {
      "sourceBoardId": "227",
      "sourceBoardName": "immigration-monthly-statistics",
      "articleId": "606790",
      "articleTitle": "2026년 4월 출입국외국인정책 통계월보",
      "publishedAt": "2026.05.21",
      "attachmentId": "495554",
      "attachmentName": "1.3. 체류외국인 원본 통계표(4월).xlsx",
      "attachmentUrl": "https://www.immigration.go.kr/bbs/immigration/227/495554/download.do",
      "localPath": "data/raw/2026/2026-04/1.3. 체류외국인 원본 통계표(4월).xlsx",
      "downloadedAt": "2026-06-24T01:08:30.553Z",
      "status": "downloaded",
      "checksum": "aa73920660a1fb8a0714d86fb944d414baff3a59ed365d56f2f3700ac382a08b"
    },
    {
      "sourceBoardId": "227",
      "sourceBoardName": "immigration-monthly-statistics",
      "articleId": "608714",
      "articleTitle": "2026년 6월 출입국외국인정책 통계월보",
      "publishedAt": "2026.07.22",
      "attachmentId": "497405",
      "attachmentName": "1.2. 외국인입국자(6월).xlsx",
      "attachmentUrl": "https://www.immigration.go.kr/bbs/immigration/227/497405/download.do",
      "localPath": "data/raw/2026/2026-06/1.2. 외국인입국자(6월).xlsx",
      "downloadedAt": "2026-07-23T05:57:20.574Z",
      "status": "downloaded",
      "checksum": "5bc398b2b217ff43debfc8146f6dd843c026ec2529cefc87b2d1b3c23dc312ac"
    }
  ]
}
